[
  {
    "incidentNumber": "61453",
    "code": "MED",
    "time": "12:26am",
    "address": "1900 Block Liberty Road"
  },
  {
    "incidentNumber": "61455",
    "code": "MED",
    "time": "12:34am",
    "address": "100 Block Opportunity Way"
  },
  {
    "incidentNumber": "61454",
    "code": "FLIFT",
    "time": "12:34am",
    "address": "1601 Villa Medici Pass"
  },
  {
    "incidentNumber": "61457",
    "code": "FELS",
    "time": "12:42am",
    "address": "720 Woodland Ave"
  },
  {
    "incidentNumber": "61456",
    "code": "MED",
    "time": "12:42am",
    "address": "700 Block W Main Street"
  },
  {
    "incidentNumber": "61458",
    "code": "MED",
    "time": "12:58am",
    "address": "700 Block Ward Drive"
  },
  {
    "incidentNumber": "61459",
    "code": "MED",
    "time": "1:06am",
    "address": "100 Block S Upper Street"
  },
  {
    "incidentNumber": "61463",
    "code": "FLIFT",
    "time": "1:22am",
    "address": "725 Troy Trl"
  },
  {
    "incidentNumber": "61462",
    "code": "FPRT",
    "time": "1:22am",
    "address": "450 W Reynolds Rd"
  },
  {
    "incidentNumber": "61461",
    "code": "FPRT",
    "time": "1:22am",
    "address": "410 Redding Rd"
  },
  {
    "incidentNumber": "61460",
    "code": "FVEA",
    "time": "1:22am",
    "address": "E Loudon Ave & Maple Ave"
  },
  {
    "incidentNumber": "61468",
    "code": "MED",
    "time": "2:02am",
    "address": "1700 Block Russell Cave Road"
  },
  {
    "incidentNumber": "61467",
    "code": "MED",
    "time": "2:02am",
    "address": "100 Block Transcript Avenue"
  },
  {
    "incidentNumber": "61466",
    "code": "FPRT",
    "time": "2:02am",
    "address": "440 Pennsylvania Ave"
  },
  {
    "incidentNumber": "61465",
    "code": "MED",
    "time": "2:02am",
    "address": "4500 Block Longbridge Lane"
  },
  {
    "incidentNumber": "61469",
    "code": "MED",
    "time": "2:10am",
    "address": "600 Block Old Frankfort Circle"
  },
  {
    "incidentNumber": "61466",
    "code": "FPRT",
    "time": "2:18am",
    "address": "440 Pennsylvania Ave"
  },
  {
    "incidentNumber": "61470",
    "code": "MED",
    "time": "2:26am",
    "address": "100 Block Market Street"
  },
  {
    "incidentNumber": "61475",
    "code": "MED",
    "time": "2:34am",
    "address": "300 Block W Short Street"
  },
  {
    "incidentNumber": "61474",
    "code": "MED",
    "time": "2:34am",
    "address": "100 Block Rose Street"
  },
  {
    "incidentNumber": "61473",
    "code": "MED",
    "time": "2:34am",
    "address": "200 Block E Main Street"
  },
  {
    "incidentNumber": "61472",
    "code": "FVEA",
    "time": "2:34am",
    "address": "466 Curry Ave"
  },
  {
    "incidentNumber": "61471",
    "code": "MED",
    "time": "2:34am",
    "address": "1400 Block Townley Drive"
  },
  {
    "incidentNumber": "61477",
    "code": "MED",
    "time": "2:50am",
    "address": "400 Block Campbell Street"
  },
  {
    "incidentNumber": "61476",
    "code": "FPRT",
    "time": "2:50am",
    "address": "164 Lakeshore Dr"
  },
  {
    "incidentNumber": "61478",
    "code": "MED",
    "time": "2:58am",
    "address": "100 Block Market Street"
  },
  {
    "incidentNumber": "61479",
    "code": "MED",
    "time": "3:14am",
    "address": "500 Block Euclid Avenue"
  },
  {
    "incidentNumber": "61480",
    "code": "MED",
    "time": "3:38am",
    "address": "300 Block White Oak Trce"
  },
  {
    "incidentNumber": "61483",
    "code": "MED",
    "time": "3:54am",
    "address": "300 Block Newtown Pike"
  },
  {
    "incidentNumber": "61482",
    "code": "MED",
    "time": "3:54am",
    "address": "S Mill St & W Main St"
  },
  {
    "incidentNumber": "61481",
    "code": "FSIA",
    "time": "3:54am",
    "address": "310 S Limestone"
  },
  {
    "incidentNumber": "61484",
    "code": "MED",
    "time": "4:02am",
    "address": "100 Block Deweese Street"
  },
  {
    "incidentNumber": "61485",
    "code": "MED",
    "time": "4:10am",
    "address": "4800 Block Versailles Road"
  },
  {
    "incidentNumber": "61486",
    "code": "FLIFT",
    "time": "4:26am",
    "address": "471 Price Rd"
  },
  {
    "incidentNumber": "61487",
    "code": "MED",
    "time": "4:51am",
    "address": "700 Block N Broadway"
  },
  {
    "incidentNumber": "61488",
    "code": "MED",
    "time": "4:59am",
    "address": "800 Block Gerardi Road"
  },
  {
    "incidentNumber": "61489",
    "code": "FMEA",
    "time": "5:15am",
    "address": "3970 Northampton Dr"
  },
  {
    "incidentNumber": "61490",
    "code": "FINV",
    "time": "5:31am",
    "address": "2050 Garden Springs Dr"
  },
  {
    "incidentNumber": "61491",
    "code": "FLIFT",
    "time": "5:39am",
    "address": "701 Liberty Ridge Ln"
  },
  {
    "incidentNumber": "61492",
    "code": "MED",
    "time": "6:03am",
    "address": "1800 Block Little Herb Way"
  },
  {
    "incidentNumber": "61493",
    "code": "MED",
    "time": "6:11am",
    "address": "1600 Block Thames Drive"
  },
  {
    "incidentNumber": "61494",
    "code": "FLIFT",
    "time": "6:27am",
    "address": "2050 Garden Springs Dr"
  },
  {
    "incidentNumber": "61497",
    "code": "MED",
    "time": "6:35am",
    "address": "3800 Block Joshua Circle"
  },
  {
    "incidentNumber": "61496",
    "code": "MED",
    "time": "6:35am",
    "address": "1500 Block Versailles Road"
  },
  {
    "incidentNumber": "61495",
    "code": "MED",
    "time": "6:35am",
    "address": "3500 Block Pimlico Parkway"
  },
  {
    "incidentNumber": "61498",
    "code": "MED",
    "time": "7:23am",
    "address": "Richmond Rd & Man O War Blvd"
  },
  {
    "incidentNumber": "61499",
    "code": "MED",
    "time": "7:31am",
    "address": "1300 Block Versailles Road"
  },
  {
    "incidentNumber": "61500",
    "code": "MED",
    "time": "8:03am",
    "address": "800 Block W Maxwell Street"
  },
  {
    "incidentNumber": "61502",
    "code": "MED",
    "time": "8:59am",
    "address": "3400 Block Heritage Pl"
  },
  {
    "incidentNumber": "61503",
    "code": "FINV",
    "time": "9:07am",
    "address": "3901 Castlebridge Ln"
  },
  {
    "incidentNumber": "61504",
    "code": "FMEA",
    "time": "9:15am",
    "address": "1513 Versailles Rd"
  },
  {
    "incidentNumber": "61505",
    "code": "MED",
    "time": "9:31am",
    "address": "400 Block Scottsdale Circle"
  },
  {
    "incidentNumber": "61506",
    "code": "MED",
    "time": "9:47am",
    "address": "1500 Block Versailles Road"
  },
  {
    "incidentNumber": "61507",
    "code": "MED",
    "time": "9:55am",
    "address": "2000 Block New Orleans Drive"
  },
  {
    "incidentNumber": "61509",
    "code": "MED",
    "time": "10:03am",
    "address": "3200 Block Lansdowne Drive"
  },
  {
    "incidentNumber": "61508",
    "code": "MED",
    "time": "10:03am",
    "address": "1000 Block Tanbark Road"
  },
  {
    "incidentNumber": "61510",
    "code": "MED",
    "time": "10:11am",
    "address": "1800 Block Little Herb Way"
  },
  {
    "incidentNumber": "61512",
    "code": "FINV",
    "time": "10:35am",
    "address": "505 W Main St"
  },
  {
    "incidentNumber": "61513",
    "code": "MED",
    "time": "10:43am",
    "address": "1800 Block Chatsworth Drive"
  },
  {
    "incidentNumber": "61514",
    "code": "FLIFT",
    "time": "10:59am",
    "address": "1447 Antique Dr"
  },
  {
    "incidentNumber": "61516",
    "code": "FLIFT",
    "time": "11:07am",
    "address": "2700 Man O War Blvd"
  },
  {
    "incidentNumber": "61515",
    "code": "MED",
    "time": "11:07am",
    "address": "2300 Block Richmond Road"
  },
  {
    "incidentNumber": "61517",
    "code": "MED",
    "time": "11:15am",
    "address": "600 Block Triple Crown Parkway"
  },
  {
    "incidentNumber": "61518",
    "code": "MED",
    "time": "11:23am",
    "address": "3400 Block Milam Lane"
  },
  {
    "incidentNumber": "61520",
    "code": "MED",
    "time": "11:31am",
    "address": "9200 Block Hickory Hill Road"
  },
  {
    "incidentNumber": "61519",
    "code": "FINV",
    "time": "11:31am",
    "address": "3901 Castlebridge Ln"
  },
  {
    "incidentNumber": "61521",
    "code": "MED",
    "time": "11:39am",
    "address": "3300 Block Leestown Road"
  },
  {
    "incidentNumber": "61524",
    "code": "MED",
    "time": "11:55am",
    "address": "200 Block E Vine Street"
  },
  {
    "incidentNumber": "61523",
    "code": "FLIFT",
    "time": "11:55am",
    "address": "2705 Green Valley Ct"
  },
  {
    "incidentNumber": "61522",
    "code": "FLIFT",
    "time": "11:55am",
    "address": "2050 Garden Springs Dr"
  },
  {
    "incidentNumber": "61526",
    "code": "MED",
    "time": "12:03pm",
    "address": "3800 Block Camelot Drive"
  },
  {
    "incidentNumber": "61525",
    "code": "FPRT",
    "time": "12:03pm",
    "address": "1340 Cooper Dr"
  },
  {
    "incidentNumber": "61527",
    "code": "MED",
    "time": "12:11pm",
    "address": "1100 Block Monarch Street"
  },
  {
    "incidentNumber": "61528",
    "code": "MED",
    "time": "12:19pm",
    "address": "1100 Block Mt Rushmore Way"
  },
  {
    "incidentNumber": "61529",
    "code": "MED",
    "time": "12:27pm",
    "address": "700 Block Mason Headley Road"
  },
  {
    "incidentNumber": "61530",
    "code": "MED",
    "time": "12:35pm",
    "address": "2500 Block Old Rosebud Road"
  },
  {
    "incidentNumber": "61531",
    "code": "MED",
    "time": "12:59pm",
    "address": "3100 Block Pine Straw Court"
  },
  {
    "incidentNumber": "61533",
    "code": "MED",
    "time": "1:07pm",
    "address": "1000 Block Crimson Creek Drive"
  },
  {
    "incidentNumber": "61532",
    "code": "MED",
    "time": "1:07pm",
    "address": "100 Block Delmont Drive"
  },
  {
    "incidentNumber": "61535",
    "code": "MED",
    "time": "1:31pm",
    "address": "200 Block Avenue Of Champions"
  },
  {
    "incidentNumber": "61534",
    "code": "MED",
    "time": "1:31pm",
    "address": "S Limestone & W High St"
  },
  {
    "incidentNumber": "61538",
    "code": "MED",
    "time": "1:39pm",
    "address": "200 Block Ruccio Way"
  },
  {
    "incidentNumber": "61537",
    "code": "MED",
    "time": "1:39pm",
    "address": "600 Block Old Frankfort Circle"
  },
  {
    "incidentNumber": "61536",
    "code": "MED",
    "time": "1:39pm",
    "address": "1800 Block Dunkirk Drive"
  },
  {
    "incidentNumber": "61541",
    "code": "MED",
    "time": "1:55pm",
    "address": "500 Block De Roode Street"
  },
  {
    "incidentNumber": "61540",
    "code": "FSTRW",
    "time": "1:55pm",
    "address": "977 Harp Innis Rd"
  },
  {
    "incidentNumber": "61539",
    "code": "MED",
    "time": "1:55pm",
    "address": "100 Block Rose Street"
  },
  {
    "incidentNumber": "61543",
    "code": "MED",
    "time": "2:19pm",
    "address": "300 Block Newtown Pike"
  },
  {
    "incidentNumber": "61542",
    "code": "MED",
    "time": "2:19pm",
    "address": "400 Block Gibson Avenue"
  },
  {
    "incidentNumber": "61544",
    "code": "MED",
    "time": "2:35pm",
    "address": "400 Block Bainbridge Court"
  }
]