[
  {
    "incidentNumber": "33819",
    "code": "MED",
    "time": "12:02am",
    "address": "100 Block W Vine Street"
  },
  {
    "incidentNumber": "33820",
    "code": "MED",
    "time": "12:29am",
    "address": "1000 Block Industry Road"
  },
  {
    "incidentNumber": "33821",
    "code": "FLOI",
    "time": "12:32am",
    "address": "1988 Pavilion Way"
  },
  {
    "incidentNumber": "33822",
    "code": "MED",
    "time": "12:41am",
    "address": "1000 Block E New Circle Road"
  },
  {
    "incidentNumber": "33823",
    "code": "MED",
    "time": "12:43am",
    "address": "2300 Block Paris Pike"
  },
  {
    "incidentNumber": "33824",
    "code": "MED",
    "time": "1:04am",
    "address": "2600 Block Wilhite Drive"
  },
  {
    "incidentNumber": "33825",
    "code": "MED",
    "time": "1:23am",
    "address": "600 Block Adcolor Drive"
  },
  {
    "incidentNumber": "33826",
    "code": "MED",
    "time": "1:29am",
    "address": "900 Block Beaumont Centre Parkway"
  },
  {
    "incidentNumber": "33827",
    "code": "MED",
    "time": "1:33am",
    "address": "3300 Block Carriage Lane"
  },
  {
    "incidentNumber": "33828",
    "code": "MED",
    "time": "2:00am",
    "address": "400 Block Whispering Hills Drive"
  },
  {
    "incidentNumber": "33829",
    "code": "FCAR",
    "time": "2:04am",
    "address": "2587 Edgehill Dr"
  },
  {
    "incidentNumber": "33830",
    "code": "MED",
    "time": "2:32am",
    "address": "700 Block W Main Street"
  },
  {
    "incidentNumber": "33831",
    "code": "MED",
    "time": "2:44am",
    "address": "3500 Block Pimlico Parkway"
  },
  {
    "incidentNumber": "33832",
    "code": "MED",
    "time": "2:46am",
    "address": "300 Block Redding Road"
  },
  {
    "incidentNumber": "33834",
    "code": "MED",
    "time": "3:38am",
    "address": "1000 Block Pine Bloom Drive"
  },
  {
    "incidentNumber": "33835",
    "code": "MED",
    "time": "3:57am",
    "address": "2800 Block Michelle Park"
  },
  {
    "incidentNumber": "33836",
    "code": "MED",
    "time": "3:58am",
    "address": "2000 Block Versailles Road"
  },
  {
    "incidentNumber": "33837",
    "code": "FVEA",
    "time": "4:07am",
    "address": "Detroit Ave & Dallas Ave"
  },
  {
    "incidentNumber": "33838",
    "code": "FPRT",
    "time": "4:13am",
    "address": "421 Redding Rd"
  },
  {
    "incidentNumber": "33839",
    "code": "MED",
    "time": "4:15am",
    "address": "1000 Block S Broadway"
  },
  {
    "incidentNumber": "33840",
    "code": "MED",
    "time": "4:39am",
    "address": "400 Block Price Road"
  },
  {
    "incidentNumber": "33841",
    "code": "FVEA",
    "time": "4:42am",
    "address": "Paris Pike & Old Paris Rd"
  },
  {
    "incidentNumber": "33842",
    "code": "MED",
    "time": "4:43am",
    "address": "3100 Block Pine Straw Court"
  },
  {
    "incidentNumber": "33843",
    "code": "MED",
    "time": "5:01am",
    "address": "3900 Block Northampton Drive"
  },
  {
    "incidentNumber": "33844",
    "code": "MED",
    "time": "5:08am",
    "address": "1000 Block Ramblewood Way"
  },
  {
    "incidentNumber": "33845",
    "code": "MED",
    "time": "5:15am",
    "address": "400 Block S Ashland Avenue"
  },
  {
    "incidentNumber": "33846",
    "code": "MED",
    "time": "5:21am",
    "address": "100 Block Canebrake Drive"
  },
  {
    "incidentNumber": "33847",
    "code": "MED",
    "time": "5:59am",
    "address": "400 Block Dominican Drive"
  },
  {
    "incidentNumber": "33848",
    "code": "MED",
    "time": "6:10am",
    "address": "1800 Block Richmond Road"
  },
  {
    "incidentNumber": "33849",
    "code": "MED",
    "time": "6:13am",
    "address": "500 Block Asbury Lane"
  },
  {
    "incidentNumber": "33850",
    "code": "FLIFT",
    "time": "6:19am",
    "address": "137 Rose St"
  },
  {
    "incidentNumber": "33851",
    "code": "MED",
    "time": "6:24am",
    "address": "3300 Block Tates Creek Road"
  },
  {
    "incidentNumber": "33852",
    "code": "FSMO",
    "time": "6:25am",
    "address": "1285 Centre Pkwy"
  },
  {
    "incidentNumber": "33853",
    "code": "MED",
    "time": "6:33am",
    "address": "500 Block Hollow Creek Road"
  },
  {
    "incidentNumber": "33854",
    "code": "MED",
    "time": "6:47am",
    "address": "2200 Block Stone Garden Lane"
  },
  {
    "incidentNumber": "33855",
    "code": "MED",
    "time": "7:01am",
    "address": "300 Block Newtown Pike"
  },
  {
    "incidentNumber": "33856",
    "code": "MED",
    "time": "7:11am",
    "address": "2600 Block Research Park Drive"
  },
  {
    "incidentNumber": "33857",
    "code": "MED",
    "time": "7:26am",
    "address": "200 Block Twelfth Street"
  },
  {
    "incidentNumber": "33858",
    "code": "MED",
    "time": "7:32am",
    "address": "2100 Block Mona Court"
  },
  {
    "incidentNumber": "33859",
    "code": "MED",
    "time": "7:42am",
    "address": "Walton Ave & Winchester Rd"
  },
  {
    "incidentNumber": "33860",
    "code": "MED",
    "time": "7:52am",
    "address": "2000 Block Versailles Road"
  },
  {
    "incidentNumber": "33861",
    "code": "MED",
    "time": "8:01am",
    "address": "2300 Block Ice House Way"
  },
  {
    "incidentNumber": "33862",
    "code": "MED",
    "time": "8:11am",
    "address": "500 Block W Second Street"
  },
  {
    "incidentNumber": "33863",
    "code": "FVEA",
    "time": "8:15am",
    "address": "Tates Creek Rd & Man O War Blv"
  },
  {
    "incidentNumber": "33864",
    "code": "FINV",
    "time": "8:17am",
    "address": "2321 Sir Barton Way"
  },
  {
    "incidentNumber": "33865",
    "code": "MED",
    "time": "8:22am",
    "address": "3300 Block Tates Creek Road"
  },
  {
    "incidentNumber": "33866",
    "code": "FPRT",
    "time": "8:33am",
    "address": "1349 Centre Pkwy"
  },
  {
    "incidentNumber": "33868",
    "code": "MED",
    "time": "8:40am",
    "address": "1800 Block Little Herb Way"
  },
  {
    "incidentNumber": "33867",
    "code": "FPRT",
    "time": "8:40am",
    "address": "3310 Tates Creek Rd"
  },
  {
    "incidentNumber": "33869",
    "code": "MED",
    "time": "8:54am",
    "address": "700 Block W Main Street"
  },
  {
    "incidentNumber": "33870",
    "code": "MED",
    "time": "9:05am",
    "address": "1200 Block Greendale Road"
  },
  {
    "incidentNumber": "33871",
    "code": "MED",
    "time": "9:07am",
    "address": "600 Block Seattle Drive"
  },
  {
    "incidentNumber": "33873",
    "code": "MED",
    "time": "9:18am",
    "address": "W Third St & Blackburn Ave"
  },
  {
    "incidentNumber": "33872",
    "code": "FLIFT",
    "time": "9:18am",
    "address": "2425 Windwood Ct"
  },
  {
    "incidentNumber": "33874",
    "code": "FLIFT",
    "time": "9:25am",
    "address": "2773 Red Clover Ln"
  },
  {
    "incidentNumber": "33875",
    "code": "MED",
    "time": "9:30am",
    "address": "2000 Block Versailles Road"
  },
  {
    "incidentNumber": "33876",
    "code": "MED",
    "time": "9:40am",
    "address": "1300 Block Centre Parkway"
  },
  {
    "incidentNumber": "33878",
    "code": "MED",
    "time": "9:45am",
    "address": "700 Block Shaker Drive"
  },
  {
    "incidentNumber": "33877",
    "code": "FSCU",
    "time": "9:45am",
    "address": "Richmond Rd & Lake Park Rd"
  },
  {
    "incidentNumber": "33880",
    "code": "MED",
    "time": "9:46am",
    "address": "400 Block Darby Creek Road"
  },
  {
    "incidentNumber": "33879",
    "code": "MED",
    "time": "9:46am",
    "address": "3300 Block Boston Road"
  },
  {
    "incidentNumber": "33881",
    "code": "FLIFT",
    "time": "9:50am",
    "address": "701 Liberty Ridge Ln"
  },
  {
    "incidentNumber": "33882",
    "code": "MED",
    "time": "9:53am",
    "address": "Market St & W Short St"
  },
  {
    "incidentNumber": "33883",
    "code": "MED",
    "time": "9:54am",
    "address": "3000 Block Blenheim Way"
  },
  {
    "incidentNumber": "33884",
    "code": "MED",
    "time": "10:00am",
    "address": "2000 Block Versailles Road"
  },
  {
    "incidentNumber": "33885",
    "code": "MED",
    "time": "10:05am",
    "address": "1400 Block Versailles Road"
  },
  {
    "incidentNumber": "33887",
    "code": "MED",
    "time": "10:12am",
    "address": "400 Block Chestnut Street"
  },
  {
    "incidentNumber": "33886",
    "code": "MED",
    "time": "10:12am",
    "address": "1500 Block Trent Boulevard"
  },
  {
    "incidentNumber": "33888",
    "code": "FCAR",
    "time": "10:16am",
    "address": "252 Chippendale Cir"
  },
  {
    "incidentNumber": "33889",
    "code": "MED",
    "time": "10:23am",
    "address": "3800 Block Camelot Drive"
  },
  {
    "incidentNumber": "33890",
    "code": "MED",
    "time": "10:28am",
    "address": "3400 Block Gatewood Court"
  },
  {
    "incidentNumber": "33891",
    "code": "FDET",
    "time": "10:34am",
    "address": "522 Patterson St"
  },
  {
    "incidentNumber": "33892",
    "code": "MED",
    "time": "10:36am",
    "address": "3400 Block Campus Way"
  },
  {
    "incidentNumber": "33893",
    "code": "MED",
    "time": "10:56am",
    "address": "300 Block Chestnut Street"
  },
  {
    "incidentNumber": "33894",
    "code": "MED",
    "time": "10:58am",
    "address": "300 Block Hermitage Drive"
  },
  {
    "incidentNumber": "33895",
    "code": "MED",
    "time": "11:03am",
    "address": "900 Block Georgetown Street"
  },
  {
    "incidentNumber": "33896",
    "code": "FINV",
    "time": "11:04am",
    "address": "376 Chamberlain Dr"
  },
  {
    "incidentNumber": "33895",
    "code": "MED",
    "time": "11:05am",
    "address": "900 Block Georgetown Street"
  },
  {
    "incidentNumber": "33897",
    "code": "FDET",
    "time": "11:20am",
    "address": "522 Patterson St"
  },
  {
    "incidentNumber": "33898",
    "code": "MED",
    "time": "11:23am",
    "address": "500 Block Ohio Street"
  },
  {
    "incidentNumber": "33899",
    "code": "MED",
    "time": "11:27am",
    "address": "Man O War Blvd & Bold Bidder D"
  },
  {
    "incidentNumber": "33900",
    "code": "MED",
    "time": "11:48am",
    "address": "2300 Block Lake Park Road"
  },
  {
    "incidentNumber": "33901",
    "code": "FVEA",
    "time": "12:09pm",
    "address": "Newtown Pike & Spy Coast Ln"
  },
  {
    "incidentNumber": "33902",
    "code": "MED",
    "time": "12:10pm",
    "address": "2400 Block Harrods Pointe Trce"
  },
  {
    "incidentNumber": "33903",
    "code": "MED",
    "time": "12:14pm",
    "address": "2100 Block Stephens Lane"
  },
  {
    "incidentNumber": "33904",
    "code": "MED",
    "time": "12:16pm",
    "address": "700 Block Andover Village Drive"
  },
  {
    "incidentNumber": "33905",
    "code": "MED",
    "time": "12:25pm",
    "address": "2600 Block Woodlawn Way"
  },
  {
    "incidentNumber": "33906",
    "code": "MED",
    "time": "12:28pm",
    "address": "100 Block Eddie Street"
  },
  {
    "incidentNumber": "33907",
    "code": "MED",
    "time": "12:32pm",
    "address": "300 Block W Loudon Avenue"
  },
  {
    "incidentNumber": "33908",
    "code": "MED",
    "time": "12:38pm",
    "address": "1800 Block Dalton Court"
  },
  {
    "incidentNumber": "33909",
    "code": "FPRT",
    "time": "12:55pm",
    "address": "444 Parkway Dr"
  },
  {
    "incidentNumber": "33910",
    "code": "MED",
    "time": "12:56pm",
    "address": "100 Block N Eagle Creek Drive"
  },
  {
    "incidentNumber": "33911",
    "code": "MED",
    "time": "1:00pm",
    "address": "1100 Block Oakwood Drive"
  },
  {
    "incidentNumber": "33912",
    "code": "MED",
    "time": "1:03pm",
    "address": "400 Block Spencer Park"
  },
  {
    "incidentNumber": "33913",
    "code": "MED",
    "time": "1:16pm",
    "address": "4500 Block Iron Works Pike"
  },
  {
    "incidentNumber": "33914",
    "code": "MED",
    "time": "1:18pm",
    "address": "4800 Block Keene Road"
  },
  {
    "incidentNumber": "33915",
    "code": "MED",
    "time": "1:26pm",
    "address": "800 Block Lane Allen Road"
  }
]