[
  {
    "incidentNumber": "36790",
    "code": "MED",
    "time": "12:13am",
    "address": "2800 Block Rio Dosa Drive"
  },
  {
    "incidentNumber": "36791",
    "code": "FPRT",
    "time": "12:20am",
    "address": "129 Constitution St"
  },
  {
    "incidentNumber": "36792",
    "code": "FLIFT",
    "time": "12:42am",
    "address": "629 Wilderness Rd"
  },
  {
    "incidentNumber": "36793",
    "code": "MED",
    "time": "1:11am",
    "address": "Harrodsburg / Jessamine Co Lin"
  },
  {
    "incidentNumber": "36794",
    "code": "MED",
    "time": "1:14am",
    "address": "100 Block Cheapside"
  }
]