[
  {
    "incidentNumber": "31391",
    "code": "FVEA",
    "time": "12:03am",
    "address": "3300 Tates Creek Road"
  },
  {
    "incidentNumber": "31390",
    "code": "FVEA",
    "time": "12:03am",
    "address": "1089 S Broadway"
  },
  {
    "incidentNumber": "31392",
    "code": "FVEA",
    "time": "12:27am",
    "address": "1702 Charleston Court"
  },
  {
    "incidentNumber": "31393",
    "code": "MED",
    "time": "12:31am",
    "address": "200 Block W Loudon Avenue"
  },
  {
    "incidentNumber": "31394",
    "code": "MED",
    "time": "12:35am",
    "address": "300 Block W Vine Street"
  },
  {
    "incidentNumber": "31395",
    "code": "MED",
    "time": "1:15am",
    "address": "600 Block Eureka Springs Drive"
  }
]