[
  {
    "incidentNumber": "50304",
    "code": "MED",
    "time": "12:06am",
    "address": "1400 Block Alexandria Drive"
  },
  {
    "incidentNumber": "50305",
    "code": "MED",
    "time": "12:08am",
    "address": "100 Block N Limestone"
  },
  {
    "incidentNumber": "50306",
    "code": "MED",
    "time": "12:18am",
    "address": "3300 Block Tates Creek Road"
  },
  {
    "incidentNumber": "50307",
    "code": "FINV",
    "time": "12:20am",
    "address": "2477 Crescenzio Way"
  },
  {
    "incidentNumber": "50308",
    "code": "MED",
    "time": "12:26am",
    "address": "400 Block Hollow Creek Road"
  },
  {
    "incidentNumber": "50309",
    "code": "FLIFT",
    "time": "12:30am",
    "address": "3310 Tates Creek Rd"
  },
  {
    "incidentNumber": "50310",
    "code": "MED",
    "time": "12:46am",
    "address": "5500 Block Versailles Road"
  },
  {
    "incidentNumber": "50311",
    "code": "FPRT",
    "time": "12:50am",
    "address": "500 S Upper St"
  },
  {
    "incidentNumber": "50312",
    "code": "MED",
    "time": "1:46am",
    "address": "800 Block Lane Allen Road"
  },
  {
    "incidentNumber": "50313",
    "code": "MED",
    "time": "2:14am",
    "address": "2400 Block Lake Park Road"
  }
]