[
  {
    "runNumber": "33656",
    "rawCode": "MED",
    "timestamp": "2026-06-24T00:07:55.308068-04:00",
    "address": "2000 Block Harrodsburg Road",
    "extra": {
      "incidentNumber": "33656",
      "run_id": "33656",
      "address": "2000 Block Harrodsburg Road",
      "rawType": "MED",
      "typeCode": "MED",
      "alert": "10",
      "alertType": "combinedIncident",
      "activePlatoon": "P1",
      "apparatus": "E11",
      "units": "E11",
      "unitCount": "1",
      "primaryTopic": "MED",
      "commandUnits": "",
      "dedupeKey": "INCIDENT-33656"
    }
  }
]