[
  {
    "runNumber": "32317",
    "rawCode": "MED",
    "timestamp": "2026-06-17T00:34:19.281716-04:00",
    "address": "1300 Block River Park Circle",
    "extra": {
      "incidentNumber": "32317",
      "run_id": "32317",
      "address": "1300 Block River Park Circle",
      "rawType": "MED",
      "typeCode": "MED",
      "alert": "10",
      "alertType": "combinedIncident",
      "activePlatoon": "P3",
      "apparatus": "EC13",
      "units": "EC13",
      "unitCount": "1",
      "primaryTopic": "MED",
      "commandUnits": "",
      "dedupeKey": "INCIDENT-32317"
    }
  },
  {
    "runNumber": "32319",
    "rawCode": "MED",
    "timestamp": "2026-06-17T00:38:18.717287-04:00",
    "address": "500 Block Ohio Street",
    "extra": {
      "incidentNumber": "32319",
      "run_id": "32319",
      "address": "500 Block Ohio Street",
      "rawType": "MED",
      "typeCode": "MED",
      "alert": "10",
      "alertType": "combinedIncident",
      "activePlatoon": "P3",
      "apparatus": "E01,EC1",
      "units": "E01,EC1",
      "unitCount": "2",
      "primaryTopic": "MED",
      "commandUnits": "",
      "dedupeKey": "INCIDENT-32319"
    }
  },
  {
    "runNumber": "32318",
    "rawCode": "MED",
    "timestamp": "2026-06-17T00:38:21.257154-04:00",
    "address": "500 Block Dover Road",
    "extra": {
      "incidentNumber": "32318",
      "run_id": "32318",
      "address": "500 Block Dover Road",
      "rawType": "MED",
      "typeCode": "MED",
      "alert": "10",
      "alertType": "combinedIncident",
      "activePlatoon": "P3",
      "apparatus": "EC3",
      "units": "EC3",
      "unitCount": "1",
      "primaryTopic": "MED",
      "commandUnits": "",
      "dedupeKey": "INCIDENT-32318"
    }
  },
  {
    "runNumber": "32320",
    "rawCode": "FLIFT",
    "timestamp": "2026-06-17T00:42:19.686592-04:00",
    "address": "2117 Walsh Court",
    "extra": {
      "incidentNumber": "32320",
      "run_id": "32320",
      "address": "2117 Walsh Court",
      "rawType": "FLIFT",
      "typeCode": "FLIFT",
      "alert": "10",
      "alertType": "combinedIncident",
      "activePlatoon": "P3",
      "apparatus": "E02",
      "units": "E02",
      "unitCount": "1",
      "primaryTopic": "FLIFT",
      "commandUnits": "",
      "dedupeKey": "INCIDENT-32320"
    }
  },
  {
    "runNumber": "32321",
    "rawCode": "MED",
    "timestamp": "2026-06-17T01:02:20.671763-04:00",
    "address": "4700 Block Athens Walnut Hill Pike",
    "extra": {
      "incidentNumber": "32321",
      "run_id": "32321",
      "address": "4700 Block Athens Walnut Hill Pike",
      "rawType": "MED",
      "typeCode": "MED",
      "alert": "10",
      "alertType": "combinedIncident",
      "activePlatoon": "P3",
      "apparatus": "EC2",
      "units": "EC2",
      "unitCount": "1",
      "primaryTopic": "MED",
      "commandUnits": "",
      "dedupeKey": "INCIDENT-32321"
    }
  },
  {
    "runNumber": "32322",
    "rawCode": "MED",
    "timestamp": "2026-06-17T01:14:22.904457-04:00",
    "address": "600 Block Old Frankfort Circle",
    "extra": {
      "incidentNumber": "32322",
      "run_id": "32322",
      "address": "600 Block Old Frankfort Circle",
      "rawType": "MED",
      "typeCode": "MED",
      "alert": "10",
      "alertType": "combinedIncident",
      "activePlatoon": "P3",
      "apparatus": "EC5",
      "units": "EC5",
      "unitCount": "1",
      "primaryTopic": "MED",
      "commandUnits": "",
      "dedupeKey": "INCIDENT-32322"
    }
  },
  {
    "runNumber": "32323",
    "rawCode": "MED",
    "timestamp": "2026-06-17T01:54:28.898390-04:00",
    "address": "1500 Block Martha Court",
    "extra": {
      "incidentNumber": "32323",
      "run_id": "32323",
      "address": "1500 Block Martha Court",
      "rawType": "MED",
      "typeCode": "MED",
      "alert": "10",
      "alertType": "combinedIncident",
      "activePlatoon": "P3",
      "apparatus": "E02,EC8",
      "units": "E02,EC8",
      "unitCount": "2",
      "primaryTopic": "MED",
      "commandUnits": "",
      "dedupeKey": "INCIDENT-32323"
    }
  },
  {
    "runNumber": "32324",
    "rawCode": "MED",
    "timestamp": "2026-06-17T02:06:28.529995-04:00",
    "address": "2200 Block Stone Garden Lane",
    "extra": {
      "incidentNumber": "32324",
      "run_id": "32324",
      "address": "2200 Block Stone Garden Lane",
      "rawType": "MED",
      "typeCode": "MED",
      "alert": "10",
      "alertType": "combinedIncident",
      "activePlatoon": "P3",
      "apparatus": "E20,EC12",
      "units": "E20,EC12",
      "unitCount": "2",
      "primaryTopic": "MED",
      "commandUnits": "",
      "dedupeKey": "INCIDENT-32324"
    }
  },
  {
    "runNumber": "32325",
    "rawCode": "FVAJ",
    "timestamp": "2026-06-17T02:26:34.757683-04:00",
    "address": "S Upper Street & Bolivar Street",
    "extra": {
      "incidentNumber": "32325",
      "run_id": "32325",
      "address": "S Upper Street & Bolivar Street",
      "rawType": "FVAJ",
      "typeCode": "FVAJ",
      "alert": "10",
      "alertType": "combinedIncident",
      "activePlatoon": "P3",
      "apparatus": "FIRE1,E06,L02,EC7,204,241,RS1",
      "units": "FIRE1,E06,L02,EC7,204,241,RS1",
      "unitCount": "7",
      "primaryTopic": "FVAJ",
      "commandUnits": "241,204",
      "dedupeKey": "INCIDENT-32325"
    }
  },
  {
    "runNumber": "32326",
    "rawCode": "MED",
    "timestamp": "2026-06-17T02:54:35.186388-04:00",
    "address": "1500 Block Versailles Road",
    "extra": {
      "incidentNumber": "32326",
      "run_id": "32326",
      "address": "1500 Block Versailles Road",
      "rawType": "MED",
      "typeCode": "MED",
      "alert": "10",
      "alertType": "combinedIncident",
      "activePlatoon": "P3",
      "apparatus": "EC5",
      "units": "EC5",
      "unitCount": "1",
      "primaryTopic": "MED",
      "commandUnits": "",
      "dedupeKey": "INCIDENT-32326"
    }
  },
  {
    "runNumber": "32327",
    "rawCode": "FLIFT",
    "timestamp": "2026-06-17T02:58:35.364542-04:00",
    "address": "701 Liberty Ridge Lane",
    "extra": {
      "incidentNumber": "32327",
      "run_id": "32327",
      "address": "701 Liberty Ridge Lane",
      "rawType": "FLIFT",
      "typeCode": "FLIFT",
      "alert": "10",
      "alertType": "combinedIncident",
      "activePlatoon": "P3",
      "apparatus": "E21",
      "units": "E21",
      "unitCount": "1",
      "primaryTopic": "FLIFT",
      "commandUnits": "",
      "dedupeKey": "INCIDENT-32327"
    }
  },
  {
    "runNumber": "32328",
    "rawCode": "FPRT",
    "timestamp": "2026-06-17T03:42:42.510548-04:00",
    "address": "3380 Paris Pike",
    "extra": {
      "incidentNumber": "32328",
      "run_id": "32328",
      "address": "3380 Paris Pike",
      "rawType": "FPRT",
      "typeCode": "FPRT",
      "alert": "10",
      "alertType": "combinedIncident",
      "activePlatoon": "P3",
      "apparatus": "FIRE1,E08,E19,L03,201",
      "units": "FIRE1,E08,E19,L03,201",
      "unitCount": "5",
      "primaryTopic": "FPRT",
      "commandUnits": "201",
      "dedupeKey": "INCIDENT-32328"
    }
  },
  {
    "runNumber": "32329",
    "rawCode": "MED",
    "timestamp": "2026-06-17T04:18:45.506500-04:00",
    "address": "3500 Block Pimlico Parkway",
    "extra": {
      "incidentNumber": "32329",
      "run_id": "32329",
      "address": "3500 Block Pimlico Parkway",
      "rawType": "MED",
      "typeCode": "MED",
      "alert": "10",
      "alertType": "combinedIncident",
      "activePlatoon": "P3",
      "apparatus": "EC13",
      "units": "EC13",
      "unitCount": "1",
      "primaryTopic": "MED",
      "commandUnits": "",
      "dedupeKey": "INCIDENT-32329"
    }
  },
  {
    "runNumber": "32330",
    "rawCode": "MED",
    "timestamp": "2026-06-17T04:26:45.850324-04:00",
    "address": "1500 Block Martha Court",
    "extra": {
      "incidentNumber": "32330",
      "run_id": "32330",
      "address": "1500 Block Martha Court",
      "rawType": "MED",
      "typeCode": "MED",
      "alert": "10",
      "alertType": "combinedIncident",
      "activePlatoon": "P3",
      "apparatus": "EC8",
      "units": "EC8",
      "unitCount": "1",
      "primaryTopic": "MED",
      "commandUnits": "",
      "dedupeKey": "INCIDENT-32330"
    }
  },
  {
    "runNumber": "32331",
    "rawCode": "MED",
    "timestamp": "2026-06-17T05:14:52.839842-04:00",
    "address": "1500 Block Trent Boulevard",
    "extra": {
      "incidentNumber": "32331",
      "run_id": "32331",
      "address": "1500 Block Trent Boulevard",
      "rawType": "MED",
      "typeCode": "MED",
      "alert": "10",
      "alertType": "combinedIncident",
      "activePlatoon": "P3",
      "apparatus": "E16,EC13",
      "units": "E16,EC13",
      "unitCount": "2",
      "primaryTopic": "MED",
      "commandUnits": "",
      "dedupeKey": "INCIDENT-32331"
    }
  },
  {
    "runNumber": "32332",
    "rawCode": "MED",
    "timestamp": "2026-06-17T05:30:52.427911-04:00",
    "address": "300 Block W New Circle Road",
    "extra": {
      "incidentNumber": "32332",
      "run_id": "32332",
      "address": "300 Block W New Circle Road",
      "rawType": "MED",
      "typeCode": "MED",
      "alert": "10",
      "alertType": "combinedIncident",
      "activePlatoon": "P3",
      "apparatus": "EC3",
      "units": "EC3",
      "unitCount": "1",
      "primaryTopic": "MED",
      "commandUnits": "",
      "dedupeKey": "INCIDENT-32332"
    }
  },
  {
    "runNumber": "32333",
    "rawCode": "MED",
    "timestamp": "2026-06-17T05:38:53.464658-04:00",
    "address": "700 Block Ward Drive",
    "extra": {
      "incidentNumber": "32333",
      "run_id": "32333",
      "address": "700 Block Ward Drive",
      "rawType": "MED",
      "typeCode": "MED",
      "alert": "10",
      "alertType": "combinedIncident",
      "activePlatoon": "P3",
      "apparatus": "E08,EC6",
      "units": "E08,EC6",
      "unitCount": "2",
      "primaryTopic": "MED",
      "commandUnits": "",
      "dedupeKey": "INCIDENT-32333"
    }
  },
  {
    "runNumber": "32334",
    "rawCode": "MED",
    "timestamp": "2026-06-17T06:14:58.801090-04:00",
    "address": "1500 Block Martha Court",
    "extra": {
      "incidentNumber": "32334",
      "run_id": "32334",
      "address": "1500 Block Martha Court",
      "rawType": "MED",
      "typeCode": "MED",
      "alert": "10",
      "alertType": "combinedIncident",
      "activePlatoon": "P3",
      "apparatus": "EC8",
      "units": "EC8",
      "unitCount": "1",
      "primaryTopic": "MED",
      "commandUnits": "",
      "dedupeKey": "INCIDENT-32334"
    }
  },
  {
    "runNumber": "32335",
    "rawCode": "FPRT",
    "timestamp": "2026-06-17T06:39:01.590971-04:00",
    "address": "3380 Paris Pike",
    "extra": {
      "incidentNumber": "32335",
      "run_id": "32335",
      "address": "3380 Paris Pike",
      "rawType": "FPRT",
      "typeCode": "FPRT",
      "alert": "10",
      "alertType": "combinedIncident",
      "activePlatoon": "P3",
      "apparatus": "FIRE1,E08,E19,L03,201",
      "units": "FIRE1,E08,E19,L03,201",
      "unitCount": "5",
      "primaryTopic": "FPRT",
      "commandUnits": "201",
      "dedupeKey": "INCIDENT-32335"
    }
  },
  {
    "runNumber": "32336",
    "rawCode": "MED",
    "timestamp": "2026-06-17T06:43:00.630126-04:00",
    "address": "1500 Block Roanoke Road",
    "extra": {
      "incidentNumber": "32336",
      "run_id": "32336",
      "address": "1500 Block Roanoke Road",
      "rawType": "MED",
      "typeCode": "MED",
      "alert": "10",
      "alertType": "combinedIncident",
      "activePlatoon": "P3",
      "apparatus": "E14",
      "units": "E14",
      "unitCount": "1",
      "primaryTopic": "MED",
      "commandUnits": "",
      "dedupeKey": "INCIDENT-32336"
    }
  },
  {
    "runNumber": "32337",
    "rawCode": "FELS",
    "timestamp": "2026-06-17T06:47:02.976694-04:00",
    "address": "1 Street Joseph Drive",
    "extra": {
      "incidentNumber": "32337",
      "run_id": "32337",
      "address": "1 Street Joseph Drive",
      "rawType": "FELS",
      "typeCode": "FELS",
      "alert": "10",
      "alertType": "combinedIncident",
      "activePlatoon": "P3",
      "apparatus": "FIRE2,E12,L04,204",
      "units": "FIRE2,E12,L04,204",
      "unitCount": "4",
      "primaryTopic": "FELS",
      "commandUnits": "204",
      "dedupeKey": "INCIDENT-32337"
    }
  },
  {
    "runNumber": "32338",
    "rawCode": "FNGL",
    "timestamp": "2026-06-17T07:07:08.716632-04:00",
    "address": "3541 Germann Court",
    "extra": {
      "incidentNumber": "32338",
      "run_id": "32338",
      "address": "3541 Germann Court",
      "rawType": "FNGL",
      "typeCode": "FNGL",
      "alert": "10",
      "alertType": "combinedIncident",
      "activePlatoon": "P1",
      "apparatus": "FIRE2,E15,E20,L04,EC9,202,220",
      "units": "FIRE2,E15,E20,L04,EC9,202,220",
      "unitCount": "7",
      "primaryTopic": "FNGL",
      "commandUnits": "220,202",
      "dedupeKey": "INCIDENT-32338"
    }
  },
  {
    "runNumber": "32339",
    "rawCode": "MED",
    "timestamp": "2026-06-17T07:31:07.571880-04:00",
    "address": "400 Block Race Street",
    "extra": {
      "incidentNumber": "32339",
      "run_id": "32339",
      "address": "400 Block Race Street",
      "rawType": "MED",
      "typeCode": "MED",
      "alert": "10",
      "alertType": "combinedIncident",
      "activePlatoon": "P1",
      "apparatus": "E01,EC1",
      "units": "E01,EC1",
      "unitCount": "2",
      "primaryTopic": "MED",
      "commandUnits": "",
      "dedupeKey": "INCIDENT-32339"
    }
  },
  {
    "runNumber": "32341",
    "rawCode": "MED",
    "timestamp": "2026-06-17T07:51:08.304223-04:00",
    "address": "400 Block Goldon Trophy Trail",
    "extra": {
      "incidentNumber": "32341",
      "run_id": "32341",
      "address": "400 Block Goldon Trophy Trail",
      "rawType": "MED",
      "typeCode": "MED",
      "alert": "10",
      "alertType": "combinedIncident",
      "activePlatoon": "P1",
      "apparatus": "EC9",
      "units": "EC9",
      "unitCount": "1",
      "primaryTopic": "MED",
      "commandUnits": "",
      "dedupeKey": "INCIDENT-32341"
    }
  },
  {
    "runNumber": "32340",
    "rawCode": "MED",
    "timestamp": "2026-06-17T07:51:10.544722-04:00",
    "address": "1500 Block Alexandria Drive",
    "extra": {
      "incidentNumber": "32340",
      "run_id": "32340",
      "address": "1500 Block Alexandria Drive",
      "rawType": "MED",
      "typeCode": "MED",
      "alert": "10",
      "alertType": "combinedIncident",
      "activePlatoon": "P1",
      "apparatus": "EC5",
      "units": "EC5",
      "unitCount": "1",
      "primaryTopic": "MED",
      "commandUnits": "",
      "dedupeKey": "INCIDENT-32340"
    }
  },
  {
    "runNumber": "32342",
    "rawCode": "FVEA",
    "timestamp": "2026-06-17T08:23:12.903425-04:00",
    "address": "1795 Old Frankfort Pike",
    "extra": {
      "incidentNumber": "32342",
      "run_id": "32342",
      "address": "1795 Old Frankfort Pike",
      "rawType": "FVEA",
      "typeCode": "FVEA",
      "alert": "10",
      "alertType": "combinedIncident",
      "activePlatoon": "P1",
      "apparatus": "E13,EC6",
      "units": "E13,EC6",
      "unitCount": "2",
      "primaryTopic": "FVEA",
      "commandUnits": "",
      "dedupeKey": "INCIDENT-32342"
    }
  },
  {
    "runNumber": "32343",
    "rawCode": "MED",
    "timestamp": "2026-06-17T08:31:13.668455-04:00",
    "address": "3100 Block Rio Dosa Drive",
    "extra": {
      "incidentNumber": "32343",
      "run_id": "32343",
      "address": "3100 Block Rio Dosa Drive",
      "rawType": "MED",
      "typeCode": "MED",
      "alert": "10",
      "alertType": "combinedIncident",
      "activePlatoon": "P1",
      "apparatus": "EC11",
      "units": "EC11",
      "unitCount": "1",
      "primaryTopic": "MED",
      "commandUnits": "",
      "dedupeKey": "INCIDENT-32343"
    }
  },
  {
    "runNumber": "32344",
    "rawCode": "MED",
    "timestamp": "2026-06-17T08:39:15.970137-04:00",
    "address": "400 Block Georgetown Street",
    "extra": {
      "incidentNumber": "32344",
      "run_id": "32344",
      "address": "400 Block Georgetown Street",
      "rawType": "MED",
      "typeCode": "MED",
      "alert": "10",
      "alertType": "combinedIncident",
      "activePlatoon": "P1",
      "apparatus": "EC6",
      "units": "EC6",
      "unitCount": "1",
      "primaryTopic": "MED",
      "commandUnits": "",
      "dedupeKey": "INCIDENT-32344"
    }
  },
  {
    "runNumber": "32345",
    "rawCode": "MED",
    "timestamp": "2026-06-17T08:43:16.881338-04:00",
    "address": "2100 Block Harrodsburg Road",
    "extra": {
      "incidentNumber": "32345",
      "run_id": "32345",
      "address": "2100 Block Harrodsburg Road",
      "rawType": "MED",
      "typeCode": "MED",
      "alert": "10",
      "alertType": "combinedIncident",
      "activePlatoon": "P1",
      "apparatus": "EC12",
      "units": "EC12",
      "unitCount": "1",
      "primaryTopic": "MED",
      "commandUnits": "",
      "dedupeKey": "INCIDENT-32345"
    }
  },
  {
    "runNumber": "32346",
    "rawCode": "MED",
    "timestamp": "2026-06-17T08:51:17.183611-04:00",
    "address": "1100 Block Venetian Way",
    "extra": {
      "incidentNumber": "32346",
      "run_id": "32346",
      "address": "1100 Block Venetian Way",
      "rawType": "MED",
      "typeCode": "MED",
      "alert": "10",
      "alertType": "combinedIncident",
      "activePlatoon": "P1",
      "apparatus": "EC13",
      "units": "EC13",
      "unitCount": "1",
      "primaryTopic": "MED",
      "commandUnits": "",
      "dedupeKey": "INCIDENT-32346"
    }
  },
  {
    "runNumber": "32347",
    "rawCode": "MED",
    "timestamp": "2026-06-17T09:03:17.150024-04:00",
    "address": "400 Block Channing Way",
    "extra": {
      "incidentNumber": "32347",
      "run_id": "32347",
      "address": "400 Block Channing Way",
      "rawType": "MED",
      "typeCode": "MED",
      "alert": "10",
      "alertType": "combinedIncident",
      "activePlatoon": "P1",
      "apparatus": "E09,EC2",
      "units": "E09,EC2",
      "unitCount": "2",
      "primaryTopic": "MED",
      "commandUnits": "",
      "dedupeKey": "INCIDENT-32347"
    }
  },
  {
    "runNumber": "32348",
    "rawCode": "MED",
    "timestamp": "2026-06-17T09:15:21.685819-04:00",
    "address": "900 Block De Porres Avenue",
    "extra": {
      "incidentNumber": "32348",
      "run_id": "32348",
      "address": "900 Block De Porres Avenue",
      "rawType": "MED",
      "typeCode": "MED",
      "alert": "10",
      "alertType": "combinedIncident",
      "activePlatoon": "P1",
      "apparatus": "EC7",
      "units": "EC7",
      "unitCount": "1",
      "primaryTopic": "MED",
      "commandUnits": "",
      "dedupeKey": "INCIDENT-32348"
    }
  },
  {
    "runNumber": "32349",
    "rawCode": "MED",
    "timestamp": "2026-06-17T09:19:21.753077-04:00",
    "address": "4100 Block John Alden Lane",
    "extra": {
      "incidentNumber": "32349",
      "run_id": "32349",
      "address": "4100 Block John Alden Lane",
      "rawType": "MED",
      "typeCode": "MED",
      "alert": "10",
      "alertType": "combinedIncident",
      "activePlatoon": "P1",
      "apparatus": "E14,EC5",
      "units": "E14,EC5",
      "unitCount": "2",
      "primaryTopic": "MED",
      "commandUnits": "",
      "dedupeKey": "INCIDENT-32349"
    }
  },
  {
    "runNumber": "32351",
    "rawCode": "MED",
    "timestamp": "2026-06-17T09:23:21.523628-04:00",
    "address": "2400 Block Williamsburg Estates Lane",
    "extra": {
      "incidentNumber": "32351",
      "run_id": "32351",
      "address": "2400 Block Williamsburg Estates Lane",
      "rawType": "MED",
      "typeCode": "MED",
      "alert": "10",
      "alertType": "combinedIncident",
      "activePlatoon": "P1",
      "apparatus": "E11,EC1",
      "units": "E11,EC1",
      "unitCount": "2",
      "primaryTopic": "MED",
      "commandUnits": "",
      "dedupeKey": "INCIDENT-32351"
    }
  },
  {
    "runNumber": "32350",
    "rawCode": "MED",
    "timestamp": "2026-06-17T09:23:24.451727-04:00",
    "address": "Jersey Street & W Maxwell Street",
    "extra": {
      "incidentNumber": "32350",
      "run_id": "32350",
      "address": "Jersey Street & W Maxwell Street",
      "rawType": "MED",
      "typeCode": "MED",
      "alert": "10",
      "alertType": "combinedIncident",
      "activePlatoon": "P1",
      "apparatus": "RS1",
      "units": "RS1",
      "unitCount": "1",
      "primaryTopic": "MED",
      "commandUnits": "",
      "dedupeKey": "INCIDENT-32350"
    }
  },
  {
    "runNumber": "32353",
    "rawCode": "FLIFT",
    "timestamp": "2026-06-17T09:27:21.103295-04:00",
    "address": "3310 Tates Creek Road",
    "extra": {
      "incidentNumber": "32353",
      "run_id": "32353",
      "address": "3310 Tates Creek Road",
      "rawType": "FLIFT",
      "typeCode": "FLIFT",
      "alert": "10",
      "alertType": "combinedIncident",
      "activePlatoon": "P1",
      "apparatus": "E07",
      "units": "E07",
      "unitCount": "1",
      "primaryTopic": "FLIFT",
      "commandUnits": "",
      "dedupeKey": "INCIDENT-32353"
    }
  },
  {
    "runNumber": "32352",
    "rawCode": "FSIA",
    "timestamp": "2026-06-17T09:27:24.618695-04:00",
    "address": "210 Rosemont Garden",
    "extra": {
      "incidentNumber": "32352",
      "run_id": "32352",
      "address": "210 Rosemont Garden",
      "rawType": "FSIA",
      "typeCode": "FSIA",
      "alert": "10",
      "alertType": "combinedIncident",
      "activePlatoon": "P1",
      "apparatus": "FIRE1,E06,E20,204",
      "units": "FIRE1,E06,E20,204",
      "unitCount": "4",
      "primaryTopic": "FSIA",
      "commandUnits": "204",
      "dedupeKey": "INCIDENT-32352"
    }
  },
  {
    "runNumber": "32353",
    "rawCode": "MED",
    "timestamp": "2026-06-17T09:35:22.009440-04:00",
    "address": "3300 Block Tates Creek Road",
    "extra": {
      "incidentNumber": "32353",
      "run_id": "32353",
      "address": "3300 Block Tates Creek Road",
      "rawType": "MED",
      "typeCode": "MED",
      "alert": "10",
      "alertType": "combinedIncident",
      "activePlatoon": "P1",
      "apparatus": "E07,EC4",
      "units": "E07,EC4",
      "unitCount": "2",
      "primaryTopic": "MED",
      "commandUnits": "",
      "dedupeKey": "INCIDENT-32353"
    }
  },
  {
    "runNumber": "32354",
    "rawCode": "MED",
    "timestamp": "2026-06-17T09:39:22.974798-04:00",
    "address": "1700 Block Bryan Station Road",
    "extra": {
      "incidentNumber": "32354",
      "run_id": "32354",
      "address": "1700 Block Bryan Station Road",
      "rawType": "MED",
      "typeCode": "MED",
      "alert": "10",
      "alertType": "combinedIncident",
      "activePlatoon": "P1",
      "apparatus": "E08",
      "units": "E08",
      "unitCount": "1",
      "primaryTopic": "MED",
      "commandUnits": "",
      "dedupeKey": "INCIDENT-32354"
    }
  },
  {
    "runNumber": "32355",
    "rawCode": "MED",
    "timestamp": "2026-06-17T09:43:23.760990-04:00",
    "address": "1500 Block Eastland Parkway",
    "extra": {
      "incidentNumber": "32355",
      "run_id": "32355",
      "address": "1500 Block Eastland Parkway",
      "rawType": "MED",
      "typeCode": "MED",
      "alert": "10",
      "alertType": "combinedIncident",
      "activePlatoon": "P1",
      "apparatus": "EC8",
      "units": "EC8",
      "unitCount": "1",
      "primaryTopic": "MED",
      "commandUnits": "",
      "dedupeKey": "INCIDENT-32355"
    }
  },
  {
    "runNumber": "32357",
    "rawCode": "MED",
    "timestamp": "2026-06-17T09:51:24.742405-04:00",
    "address": "200 Block E New Circle Road",
    "extra": {
      "incidentNumber": "32357",
      "run_id": "32357",
      "address": "200 Block E New Circle Road",
      "rawType": "MED",
      "typeCode": "MED",
      "alert": "10",
      "alertType": "combinedIncident",
      "activePlatoon": "P1",
      "apparatus": "E02,EC6",
      "units": "E02,EC6",
      "unitCount": "2",
      "primaryTopic": "MED",
      "commandUnits": "",
      "dedupeKey": "INCIDENT-32357"
    }
  },
  {
    "runNumber": "32356",
    "rawCode": "MED",
    "timestamp": "2026-06-17T09:51:27.966115-04:00",
    "address": "3000 Block Arrowhead Drive",
    "extra": {
      "incidentNumber": "32356",
      "run_id": "32356",
      "address": "3000 Block Arrowhead Drive",
      "rawType": "MED",
      "typeCode": "MED",
      "alert": "10",
      "alertType": "combinedIncident",
      "activePlatoon": "P1",
      "apparatus": "EC9",
      "units": "EC9",
      "unitCount": "1",
      "primaryTopic": "MED",
      "commandUnits": "",
      "dedupeKey": "INCIDENT-32356"
    }
  },
  {
    "runNumber": "32359",
    "rawCode": "MED",
    "timestamp": "2026-06-17T09:59:25.555851-04:00",
    "address": "1800 Block Georgetown Road",
    "extra": {
      "incidentNumber": "32359",
      "run_id": "32359",
      "address": "1800 Block Georgetown Road",
      "rawType": "MED",
      "typeCode": "MED",
      "alert": "10",
      "alertType": "combinedIncident",
      "activePlatoon": "P1",
      "apparatus": "E10,EC10",
      "units": "E10,EC10",
      "unitCount": "2",
      "primaryTopic": "MED",
      "commandUnits": "",
      "dedupeKey": "INCIDENT-32359"
    }
  },
  {
    "runNumber": "32358",
    "rawCode": "MED",
    "timestamp": "2026-06-17T09:59:28.739124-04:00",
    "address": "2700 Block Michelle Park",
    "extra": {
      "incidentNumber": "32358",
      "run_id": "32358",
      "address": "2700 Block Michelle Park",
      "rawType": "MED",
      "typeCode": "MED",
      "alert": "10",
      "alertType": "combinedIncident",
      "activePlatoon": "P1",
      "apparatus": "E24,EC12",
      "units": "E24,EC12",
      "unitCount": "2",
      "primaryTopic": "MED",
      "commandUnits": "",
      "dedupeKey": "INCIDENT-32358"
    }
  },
  {
    "runNumber": "32360",
    "rawCode": "MED",
    "timestamp": "2026-06-17T10:03:25.631064-04:00",
    "address": "2600 Block Colrain Court",
    "extra": {
      "incidentNumber": "32360",
      "run_id": "32360",
      "address": "2600 Block Colrain Court",
      "rawType": "MED",
      "typeCode": "MED",
      "alert": "10",
      "alertType": "combinedIncident",
      "activePlatoon": "P1",
      "apparatus": "CRT1",
      "units": "CRT1",
      "unitCount": "1",
      "primaryTopic": "MED",
      "commandUnits": "",
      "dedupeKey": "INCIDENT-32360"
    }
  },
  {
    "runNumber": "32361",
    "rawCode": "FFIA",
    "timestamp": "2026-06-17T10:07:26.724889-04:00",
    "address": "2035 Altamont Court",
    "extra": {
      "incidentNumber": "32361",
      "run_id": "32361",
      "address": "2035 Altamont Court",
      "rawType": "FFIA",
      "typeCode": "FFIA",
      "alert": "10",
      "alertType": "combinedIncident",
      "activePlatoon": "P1",
      "apparatus": "FIRE1,E09,E21,L06,EC13,201",
      "units": "FIRE1,E09,E21,L06,EC13,201",
      "unitCount": "6",
      "primaryTopic": "FFIA",
      "commandUnits": "201",
      "dedupeKey": "INCIDENT-32361"
    }
  },
  {
    "runNumber": "32362",
    "rawCode": "FPRT",
    "timestamp": "2026-06-17T10:15:28.896213-04:00",
    "address": "2109 Belmont Drive",
    "extra": {
      "incidentNumber": "32362",
      "run_id": "32362",
      "address": "2109 Belmont Drive",
      "rawType": "FPRT",
      "typeCode": "FPRT",
      "alert": "10",
      "alertType": "combinedIncident",
      "activePlatoon": "P1",
      "apparatus": "FIRE2,E04,E08,L03,201",
      "units": "FIRE2,E04,E08,L03,201",
      "unitCount": "5",
      "primaryTopic": "FPRT",
      "commandUnits": "201",
      "dedupeKey": "INCIDENT-32362"
    }
  },
  {
    "runNumber": "32363",
    "rawCode": "MED",
    "timestamp": "2026-06-17T10:23:28.854966-04:00",
    "address": "1900 Block Haggard Court",
    "extra": {
      "incidentNumber": "32363",
      "run_id": "32363",
      "address": "1900 Block Haggard Court",
      "rawType": "MED",
      "typeCode": "MED",
      "alert": "10",
      "alertType": "combinedIncident",
      "activePlatoon": "P1",
      "apparatus": "EC3",
      "units": "EC3",
      "unitCount": "1",
      "primaryTopic": "MED",
      "commandUnits": "",
      "dedupeKey": "INCIDENT-32363"
    }
  },
  {
    "runNumber": "32364",
    "rawCode": "MED",
    "timestamp": "2026-06-17T10:27:29.012530-04:00",
    "address": "2700 Block Richmond Road",
    "extra": {
      "incidentNumber": "32364",
      "run_id": "32364",
      "address": "2700 Block Richmond Road",
      "rawType": "MED",
      "typeCode": "MED",
      "alert": "10",
      "alertType": "combinedIncident",
      "activePlatoon": "P1",
      "apparatus": "EC13",
      "units": "EC13",
      "unitCount": "1",
      "primaryTopic": "MED",
      "commandUnits": "",
      "dedupeKey": "INCIDENT-32364"
    }
  },
  {
    "runNumber": "32365",
    "rawCode": "FLIFT",
    "timestamp": "2026-06-17T10:31:28.905636-04:00",
    "address": "1029 Summer Wind Lane",
    "extra": {
      "incidentNumber": "32365",
      "run_id": "32365",
      "address": "1029 Summer Wind Lane",
      "rawType": "FLIFT",
      "typeCode": "FLIFT",
      "alert": "10",
      "alertType": "combinedIncident",
      "activePlatoon": "P1",
      "apparatus": "E22",
      "units": "E22",
      "unitCount": "1",
      "primaryTopic": "FLIFT",
      "commandUnits": "",
      "dedupeKey": "INCIDENT-32365"
    }
  },
  {
    "runNumber": "32366",
    "rawCode": "FLIFT",
    "timestamp": "2026-06-17T10:35:29.952505-04:00",
    "address": "2117 Walsh Court",
    "extra": {
      "incidentNumber": "32366",
      "run_id": "32366",
      "address": "2117 Walsh Court",
      "rawType": "FLIFT",
      "typeCode": "FLIFT",
      "alert": "10",
      "alertType": "combinedIncident",
      "activePlatoon": "P1",
      "apparatus": "E09",
      "units": "E09",
      "unitCount": "1",
      "primaryTopic": "FLIFT",
      "commandUnits": "",
      "dedupeKey": "INCIDENT-32366"
    }
  },
  {
    "runNumber": "32368",
    "rawCode": "FELS",
    "timestamp": "2026-06-17T10:47:32.453909-04:00",
    "address": "1935 Stanton Way",
    "extra": {
      "incidentNumber": "32368",
      "run_id": "32368",
      "address": "1935 Stanton Way",
      "rawType": "FELS",
      "typeCode": "FELS",
      "alert": "10",
      "alertType": "combinedIncident",
      "activePlatoon": "P1",
      "apparatus": "FIRE1,E08,L03,203",
      "units": "FIRE1,E08,L03,203",
      "unitCount": "4",
      "primaryTopic": "FELS",
      "commandUnits": "203",
      "dedupeKey": "INCIDENT-32368"
    }
  },
  {
    "runNumber": "32367",
    "rawCode": "MED",
    "timestamp": "2026-06-17T10:47:36.576895-04:00",
    "address": "3900 Block Grassy Creek Drive",
    "extra": {
      "incidentNumber": "32367",
      "run_id": "32367",
      "address": "3900 Block Grassy Creek Drive",
      "rawType": "MED",
      "typeCode": "MED",
      "alert": "10",
      "alertType": "combinedIncident",
      "activePlatoon": "P1",
      "apparatus": "EC12",
      "units": "EC12",
      "unitCount": "1",
      "primaryTopic": "MED",
      "commandUnits": "",
      "dedupeKey": "INCIDENT-32367"
    }
  },
  {
    "runNumber": "32369",
    "rawCode": "FPRT",
    "timestamp": "2026-06-17T10:59:35.807389-04:00",
    "address": "2320 Fortune Drive",
    "extra": {
      "incidentNumber": "32369",
      "run_id": "32369",
      "address": "2320 Fortune Drive",
      "rawType": "FPRT",
      "typeCode": "FPRT",
      "alert": "10",
      "alertType": "combinedIncident",
      "activePlatoon": "P1",
      "apparatus": "FIRE1,E09,E17,L06,201",
      "units": "FIRE1,E09,E17,L06,201",
      "unitCount": "5",
      "primaryTopic": "FPRT",
      "commandUnits": "201",
      "dedupeKey": "INCIDENT-32369"
    }
  },
  {
    "runNumber": "32371",
    "rawCode": "MED",
    "timestamp": "2026-06-17T11:03:34.071634-04:00",
    "address": "300 Block Albany Road",
    "extra": {
      "incidentNumber": "32371",
      "run_id": "32371",
      "address": "300 Block Albany Road",
      "rawType": "MED",
      "typeCode": "MED",
      "alert": "10",
      "alertType": "combinedIncident",
      "activePlatoon": "P1",
      "apparatus": "E07,EC9",
      "units": "E07,EC9",
      "unitCount": "2",
      "primaryTopic": "MED",
      "commandUnits": "",
      "dedupeKey": "INCIDENT-32371"
    }
  },
  {
    "runNumber": "32370",
    "rawCode": "MED",
    "timestamp": "2026-06-17T11:03:37.324508-04:00",
    "address": "300 Block W Loudon Avenue",
    "extra": {
      "incidentNumber": "32370",
      "run_id": "32370",
      "address": "300 Block W Loudon Avenue",
      "rawType": "MED",
      "typeCode": "MED",
      "alert": "10",
      "alertType": "combinedIncident",
      "activePlatoon": "P1",
      "apparatus": "E04,EC6,CRT1",
      "units": "E04,EC6,CRT1",
      "unitCount": "3",
      "primaryTopic": "MED",
      "commandUnits": "",
      "dedupeKey": "INCIDENT-32370"
    }
  },
  {
    "runNumber": "32373",
    "rawCode": "MED",
    "timestamp": "2026-06-17T11:11:34.113784-04:00",
    "address": "3400 Block Richmond Road",
    "extra": {
      "incidentNumber": "32373",
      "run_id": "32373",
      "address": "3400 Block Richmond Road",
      "rawType": "MED",
      "typeCode": "MED",
      "alert": "10",
      "alertType": "combinedIncident",
      "activePlatoon": "P1",
      "apparatus": "EC2",
      "units": "EC2",
      "unitCount": "1",
      "primaryTopic": "MED",
      "commandUnits": "",
      "dedupeKey": "INCIDENT-32373"
    }
  },
  {
    "runNumber": "32372",
    "rawCode": "FLIFT",
    "timestamp": "2026-06-17T11:11:36.717277-04:00",
    "address": "1844 Williamsburg Road",
    "extra": {
      "incidentNumber": "32372",
      "run_id": "32372",
      "address": "1844 Williamsburg Road",
      "rawType": "FLIFT",
      "typeCode": "FLIFT",
      "alert": "10",
      "alertType": "combinedIncident",
      "activePlatoon": "P1",
      "apparatus": "E12",
      "units": "E12",
      "unitCount": "1",
      "primaryTopic": "FLIFT",
      "commandUnits": "",
      "dedupeKey": "INCIDENT-32372"
    }
  },
  {
    "runNumber": "32375",
    "rawCode": "MED",
    "timestamp": "2026-06-17T11:23:36.784118-04:00",
    "address": "4000 Block Finn Way",
    "extra": {
      "incidentNumber": "32375",
      "run_id": "32375",
      "address": "4000 Block Finn Way",
      "rawType": "MED",
      "typeCode": "MED",
      "alert": "10",
      "alertType": "combinedIncident",
      "activePlatoon": "P1",
      "apparatus": "E22,EC13",
      "units": "E22,EC13",
      "unitCount": "2",
      "primaryTopic": "MED",
      "commandUnits": "",
      "dedupeKey": "INCIDENT-32375"
    }
  },
  {
    "runNumber": "32374",
    "rawCode": "FSMO",
    "timestamp": "2026-06-17T11:23:41.224156-04:00",
    "address": "744 Bellaire Avenue",
    "extra": {
      "incidentNumber": "32374",
      "run_id": "32374",
      "address": "744 Bellaire Avenue",
      "rawType": "FSMO",
      "typeCode": "FSMO",
      "alert": "10",
      "alertType": "combinedIncident",
      "activePlatoon": "P1",
      "apparatus": "FIRE1,E04,E10,L03,EC3,201",
      "units": "FIRE1,E04,E10,L03,EC3,201",
      "unitCount": "6",
      "primaryTopic": "FSMO",
      "commandUnits": "201",
      "dedupeKey": "INCIDENT-32374"
    }
  },
  {
    "runNumber": "32376",
    "rawCode": "MED",
    "timestamp": "2026-06-17T11:27:37.755775-04:00",
    "address": "2700 Block Jessica Lane",
    "extra": {
      "incidentNumber": "32376",
      "run_id": "32376",
      "address": "2700 Block Jessica Lane",
      "rawType": "MED",
      "typeCode": "MED",
      "alert": "10",
      "alertType": "combinedIncident",
      "activePlatoon": "P1",
      "apparatus": "EC6",
      "units": "EC6",
      "unitCount": "1",
      "primaryTopic": "MED",
      "commandUnits": "",
      "dedupeKey": "INCIDENT-32376"
    }
  },
  {
    "runNumber": "32377",
    "rawCode": "FINV",
    "timestamp": "2026-06-17T11:43:39.501161-04:00",
    "address": "3629 Mossbridge Way",
    "extra": {
      "incidentNumber": "32377",
      "run_id": "32377",
      "address": "3629 Mossbridge Way",
      "rawType": "FINV",
      "typeCode": "FINV",
      "alert": "10",
      "alertType": "combinedIncident",
      "activePlatoon": "P1",
      "apparatus": "E22",
      "units": "E22",
      "unitCount": "1",
      "primaryTopic": "FINV",
      "commandUnits": "",
      "dedupeKey": "INCIDENT-32377"
    }
  },
  {
    "runNumber": "32378",
    "rawCode": "FPRT",
    "timestamp": "2026-06-17T11:55:41.906624-04:00",
    "address": "333 S Limestone",
    "extra": {
      "incidentNumber": "32378",
      "run_id": "32378",
      "address": "333 S Limestone",
      "rawType": "FPRT",
      "typeCode": "FPRT",
      "alert": "10",
      "alertType": "combinedIncident",
      "activePlatoon": "P1",
      "apparatus": "FIRE1,E04,E06,L01,205",
      "units": "FIRE1,E04,E06,L01,205",
      "unitCount": "5",
      "primaryTopic": "FPRT",
      "commandUnits": "205",
      "dedupeKey": "INCIDENT-32378"
    }
  },
  {
    "runNumber": "32379",
    "rawCode": "FNGL",
    "timestamp": "2026-06-17T11:59:44.672020-04:00",
    "address": "3090 Harrodsburg Road",
    "extra": {
      "incidentNumber": "32379",
      "run_id": "32379",
      "address": "3090 Harrodsburg Road",
      "rawType": "FNGL",
      "typeCode": "FNGL",
      "alert": "10",
      "alertType": "combinedIncident",
      "activePlatoon": "P1",
      "apparatus": "FIRE2,E11,E20,L04,EC5,204,220",
      "units": "FIRE2,E11,E20,L04,EC5,204,220",
      "unitCount": "7",
      "primaryTopic": "FNGL",
      "commandUnits": "220,204",
      "dedupeKey": "INCIDENT-32379"
    }
  },
  {
    "runNumber": "32382",
    "rawCode": "MED",
    "timestamp": "2026-06-17T12:07:42.737784-04:00",
    "address": "2700 Block Man O War Boulevard",
    "extra": {
      "incidentNumber": "32382",
      "run_id": "32382",
      "address": "2700 Block Man O War Boulevard",
      "rawType": "MED",
      "typeCode": "MED",
      "alert": "10",
      "alertType": "combinedIncident",
      "activePlatoon": "P1",
      "apparatus": "E15,EC12",
      "units": "E15,EC12",
      "unitCount": "2",
      "primaryTopic": "MED",
      "commandUnits": "",
      "dedupeKey": "INCIDENT-32382"
    }
  },
  {
    "runNumber": "32381",
    "rawCode": "FBGL",
    "timestamp": "2026-06-17T12:07:45.634688-04:00",
    "address": "1760 Harrodsburg Road",
    "extra": {
      "incidentNumber": "32381",
      "run_id": "32381",
      "address": "1760 Harrodsburg Road",
      "rawType": "FBGL",
      "typeCode": "FBGL",
      "alert": "10",
      "alertType": "combinedIncident",
      "activePlatoon": "P1",
      "apparatus": "E12",
      "units": "E12",
      "unitCount": "1",
      "primaryTopic": "FBGL",
      "commandUnits": "",
      "dedupeKey": "INCIDENT-32381"
    }
  },
  {
    "runNumber": "32380",
    "rawCode": "MED",
    "timestamp": "2026-06-17T12:07:47.736472-04:00",
    "address": "100 Block Lakeshore Drive",
    "extra": {
      "incidentNumber": "32380",
      "run_id": "32380",
      "address": "100 Block Lakeshore Drive",
      "rawType": "MED",
      "typeCode": "MED",
      "alert": "10",
      "alertType": "combinedIncident",
      "activePlatoon": "P1",
      "apparatus": "E09,EC2",
      "units": "E09,EC2",
      "unitCount": "2",
      "primaryTopic": "MED",
      "commandUnits": "",
      "dedupeKey": "INCIDENT-32380"
    }
  },
  {
    "runNumber": "32385",
    "rawCode": "MED",
    "timestamp": "2026-06-17T12:11:43.288909-04:00",
    "address": "100 Block Spruce Street",
    "extra": {
      "incidentNumber": "32385",
      "run_id": "32385",
      "address": "100 Block Spruce Street",
      "rawType": "MED",
      "typeCode": "MED",
      "alert": "10",
      "alertType": "combinedIncident",
      "activePlatoon": "P1",
      "apparatus": "L01,EC1",
      "units": "L01,EC1",
      "unitCount": "2",
      "primaryTopic": "MED",
      "commandUnits": "",
      "dedupeKey": "INCIDENT-32385"
    }
  },
  {
    "runNumber": "32384",
    "rawCode": "MED",
    "timestamp": "2026-06-17T12:11:46.382652-04:00",
    "address": "Versailles Road & Bennett Avenue",
    "extra": {
      "incidentNumber": "32384",
      "run_id": "32384",
      "address": "Versailles Road & Bennett Avenue",
      "rawType": "MED",
      "typeCode": "MED",
      "alert": "10",
      "alertType": "combinedIncident",
      "activePlatoon": "P1",
      "apparatus": "E01",
      "units": "E01",
      "unitCount": "1",
      "primaryTopic": "MED",
      "commandUnits": "",
      "dedupeKey": "INCIDENT-32384"
    }
  },
  {
    "runNumber": "32383",
    "rawCode": "MED",
    "timestamp": "2026-06-17T12:11:48.559264-04:00",
    "address": "4100 Block Todds Road",
    "extra": {
      "incidentNumber": "32383",
      "run_id": "32383",
      "address": "4100 Block Todds Road",
      "rawType": "MED",
      "typeCode": "MED",
      "alert": "10",
      "alertType": "combinedIncident",
      "activePlatoon": "P1",
      "apparatus": "E21,EC11",
      "units": "E21,EC11",
      "unitCount": "2",
      "primaryTopic": "MED",
      "commandUnits": "",
      "dedupeKey": "INCIDENT-32383"
    }
  },
  {
    "runNumber": "32386",
    "rawCode": "FBGL",
    "timestamp": "2026-06-17T12:15:43.004440-04:00",
    "address": "134 Malabu Drive",
    "extra": {
      "incidentNumber": "32386",
      "run_id": "32386",
      "address": "134 Malabu Drive",
      "rawType": "FBGL",
      "typeCode": "FBGL",
      "alert": "10",
      "alertType": "combinedIncident",
      "activePlatoon": "P1",
      "apparatus": "E07",
      "units": "E07",
      "unitCount": "1",
      "primaryTopic": "FBGL",
      "commandUnits": "",
      "dedupeKey": "INCIDENT-32386"
    }
  },
  {
    "runNumber": "32387",
    "rawCode": "MED",
    "timestamp": "2026-06-17T12:19:43.757030-04:00",
    "address": "3800 Block Aria Lane",
    "extra": {
      "incidentNumber": "32387",
      "run_id": "32387",
      "address": "3800 Block Aria Lane",
      "rawType": "MED",
      "typeCode": "MED",
      "alert": "10",
      "alertType": "combinedIncident",
      "activePlatoon": "P1",
      "apparatus": "E11,EC12",
      "units": "E11,EC12",
      "unitCount": "2",
      "primaryTopic": "MED",
      "commandUnits": "",
      "dedupeKey": "INCIDENT-32387"
    }
  },
  {
    "runNumber": "32388",
    "rawCode": "MED",
    "timestamp": "2026-06-17T12:27:44.588008-04:00",
    "address": "100 Block W Loudon Avenue",
    "extra": {
      "incidentNumber": "32388",
      "run_id": "32388",
      "address": "100 Block W Loudon Avenue",
      "rawType": "MED",
      "typeCode": "MED",
      "alert": "10",
      "alertType": "combinedIncident",
      "activePlatoon": "P1",
      "apparatus": "EC3",
      "units": "EC3",
      "unitCount": "1",
      "primaryTopic": "MED",
      "commandUnits": "",
      "dedupeKey": "INCIDENT-32388"
    }
  },
  {
    "runNumber": "32390",
    "rawCode": "MED",
    "timestamp": "2026-06-17T12:43:48.354434-04:00",
    "address": "600 Block Tower Plz",
    "extra": {
      "incidentNumber": "32390",
      "run_id": "32390",
      "address": "600 Block Tower Plz",
      "rawType": "MED",
      "typeCode": "MED",
      "alert": "10",
      "alertType": "combinedIncident",
      "activePlatoon": "P1",
      "apparatus": "E04,EC1",
      "units": "E04,EC1",
      "unitCount": "2",
      "primaryTopic": "MED",
      "commandUnits": "",
      "dedupeKey": "INCIDENT-32390"
    }
  },
  {
    "runNumber": "32389",
    "rawCode": "MED",
    "timestamp": "2026-06-17T12:43:52.017257-04:00",
    "address": "4000 Block Tates Creek Road",
    "extra": {
      "incidentNumber": "32389",
      "run_id": "32389",
      "address": "4000 Block Tates Creek Road",
      "rawType": "MED",
      "typeCode": "MED",
      "alert": "10",
      "alertType": "combinedIncident",
      "activePlatoon": "P1",
      "apparatus": "E22,EC13",
      "units": "E22,EC13",
      "unitCount": "2",
      "primaryTopic": "MED",
      "commandUnits": "",
      "dedupeKey": "INCIDENT-32389"
    }
  },
  {
    "runNumber": "32391",
    "rawCode": "MED",
    "timestamp": "2026-06-17T12:51:47.983341-04:00",
    "address": "100 Block Opportunity Way",
    "extra": {
      "incidentNumber": "32391",
      "run_id": "32391",
      "address": "100 Block Opportunity Way",
      "rawType": "MED",
      "typeCode": "MED",
      "alert": "10",
      "alertType": "combinedIncident",
      "activePlatoon": "P1",
      "apparatus": "E13,EC10",
      "units": "E13,EC10",
      "unitCount": "2",
      "primaryTopic": "MED",
      "commandUnits": "",
      "dedupeKey": "INCIDENT-32391"
    }
  },
  {
    "runNumber": "32393",
    "rawCode": "FVEA",
    "timestamp": "2026-06-17T12:55:48.224485-04:00",
    "address": "Richmond Road & S Locust Hill Drive",
    "extra": {
      "incidentNumber": "32393",
      "run_id": "32393",
      "address": "Richmond Road & S Locust Hill Drive",
      "rawType": "FVEA",
      "typeCode": "FVEA",
      "alert": "10",
      "alertType": "combinedIncident",
      "activePlatoon": "P1",
      "apparatus": "E09,EC8",
      "units": "E09,EC8",
      "unitCount": "2",
      "primaryTopic": "FVEA",
      "commandUnits": "",
      "dedupeKey": "INCIDENT-32393"
    }
  },
  {
    "runNumber": "32392",
    "rawCode": "FASB",
    "timestamp": "2026-06-17T12:55:51.203481-04:00",
    "address": "5751 Briar Hill Road",
    "extra": {
      "incidentNumber": "32392",
      "run_id": "32392",
      "address": "5751 Briar Hill Road",
      "rawType": "FASB",
      "typeCode": "FASB",
      "alert": "10",
      "alertType": "combinedIncident",
      "activePlatoon": "P1",
      "apparatus": "E23",
      "units": "E23",
      "unitCount": "1",
      "primaryTopic": "FASB",
      "commandUnits": "",
      "dedupeKey": "INCIDENT-32392"
    }
  },
  {
    "runNumber": "32394",
    "rawCode": "FVEH",
    "timestamp": "2026-06-17T13:15:52.109378-04:00",
    "address": "672 Blue Sky Parkway",
    "extra": {
      "incidentNumber": "32394",
      "run_id": "32394",
      "address": "672 Blue Sky Parkway",
      "rawType": "FVEH",
      "typeCode": "FVEH",
      "alert": "10",
      "alertType": "combinedIncident",
      "activePlatoon": "P1",
      "apparatus": "E09,E18",
      "units": "E09,E18",
      "unitCount": "2",
      "primaryTopic": "FVEH",
      "commandUnits": "",
      "dedupeKey": "INCIDENT-32394"
    }
  },
  {
    "runNumber": "32395",
    "rawCode": "FSTR",
    "timestamp": "2026-06-17T13:19:55.394781-04:00",
    "address": "400 Wilson Downing Road",
    "extra": {
      "incidentNumber": "32395",
      "run_id": "32395",
      "address": "400 Wilson Downing Road",
      "rawType": "FSTR",
      "typeCode": "FSTR",
      "alert": "10",
      "alertType": "combinedIncident",
      "activePlatoon": "P1",
      "apparatus": "FIRE1,E07,E08,E15,E22,L04,L07,EC9,202,204,220,RS1",
      "units": "FIRE1,E07,E08,E15,E22,L04,L07,EC9,202,204,220,RS1",
      "unitCount": "12",
      "primaryTopic": "FSTR",
      "commandUnits": "220,202,204",
      "dedupeKey": "INCIDENT-32395"
    }
  },
  {
    "runNumber": "32396",
    "rawCode": "MED",
    "timestamp": "2026-06-17T13:23:52.206114-04:00",
    "address": "1900 Block Richmond Road",
    "extra": {
      "incidentNumber": "32396",
      "run_id": "32396",
      "address": "1900 Block Richmond Road",
      "rawType": "MED",
      "typeCode": "MED",
      "alert": "10",
      "alertType": "combinedIncident",
      "activePlatoon": "P1",
      "apparatus": "E05,EC2",
      "units": "E05,EC2",
      "unitCount": "2",
      "primaryTopic": "MED",
      "commandUnits": "",
      "dedupeKey": "INCIDENT-32396"
    }
  },
  {
    "runNumber": "32398",
    "rawCode": "MED",
    "timestamp": "2026-06-17T13:27:52.405907-04:00",
    "address": "2700 Block Meadowsweet Lane",
    "extra": {
      "incidentNumber": "32398",
      "run_id": "32398",
      "address": "2700 Block Meadowsweet Lane",
      "rawType": "MED",
      "typeCode": "MED",
      "alert": "10",
      "alertType": "combinedIncident",
      "activePlatoon": "P1",
      "apparatus": "E12,EC1",
      "units": "E12,EC1",
      "unitCount": "2",
      "primaryTopic": "MED",
      "commandUnits": "",
      "dedupeKey": "INCIDENT-32398"
    }
  },
  {
    "runNumber": "32397",
    "rawCode": "MED",
    "timestamp": "2026-06-17T13:27:55.321021-04:00",
    "address": "2600 Block Colrain Court",
    "extra": {
      "incidentNumber": "32397",
      "run_id": "32397",
      "address": "2600 Block Colrain Court",
      "rawType": "MED",
      "typeCode": "MED",
      "alert": "10",
      "alertType": "combinedIncident",
      "activePlatoon": "P1",
      "apparatus": "CRT1",
      "units": "CRT1",
      "unitCount": "1",
      "primaryTopic": "MED",
      "commandUnits": "",
      "dedupeKey": "INCIDENT-32397"
    }
  },
  {
    "runNumber": "32399",
    "rawCode": "MED",
    "timestamp": "2026-06-17T13:35:53.326657-04:00",
    "address": "300 Block Larkwood Drive",
    "extra": {
      "incidentNumber": "32399",
      "run_id": "32399",
      "address": "300 Block Larkwood Drive",
      "rawType": "MED",
      "typeCode": "MED",
      "alert": "10",
      "alertType": "combinedIncident",
      "activePlatoon": "P1",
      "apparatus": "251",
      "units": "251",
      "unitCount": "1",
      "primaryTopic": "MED",
      "commandUnits": "",
      "dedupeKey": "INCIDENT-32399"
    }
  },
  {
    "runNumber": "32400",
    "rawCode": "MED",
    "timestamp": "2026-06-17T13:39:53.357028-04:00",
    "address": "3300 Block Commodore Drive",
    "extra": {
      "incidentNumber": "32400",
      "run_id": "32400",
      "address": "3300 Block Commodore Drive",
      "rawType": "MED",
      "typeCode": "MED",
      "alert": "10",
      "alertType": "combinedIncident",
      "activePlatoon": "P1",
      "apparatus": "EC13",
      "units": "EC13",
      "unitCount": "1",
      "primaryTopic": "MED",
      "commandUnits": "",
      "dedupeKey": "INCIDENT-32400"
    }
  },
  {
    "runNumber": "32401",
    "rawCode": "MED",
    "timestamp": "2026-06-17T13:47:55.580733-04:00",
    "address": "1000 Block Duval Street",
    "extra": {
      "incidentNumber": "32401",
      "run_id": "32401",
      "address": "1000 Block Duval Street",
      "rawType": "MED",
      "typeCode": "MED",
      "alert": "10",
      "alertType": "combinedIncident",
      "activePlatoon": "P1",
      "apparatus": "EC9",
      "units": "EC9",
      "unitCount": "1",
      "primaryTopic": "MED",
      "commandUnits": "",
      "dedupeKey": "INCIDENT-32401"
    }
  },
  {
    "runNumber": "32404",
    "rawCode": "MED",
    "timestamp": "2026-06-17T13:51:55.932136-04:00",
    "address": "1800 Block Versailles Road",
    "extra": {
      "incidentNumber": "32404",
      "run_id": "32404",
      "address": "1800 Block Versailles Road",
      "rawType": "MED",
      "typeCode": "MED",
      "alert": "10",
      "alertType": "combinedIncident",
      "activePlatoon": "P1",
      "apparatus": "EC12",
      "units": "EC12",
      "unitCount": "1",
      "primaryTopic": "MED",
      "commandUnits": "",
      "dedupeKey": "INCIDENT-32404"
    }
  },
  {
    "runNumber": "32403",
    "rawCode": "MED",
    "timestamp": "2026-06-17T13:51:58.360761-04:00",
    "address": "3700 Block Belleau Wood Drive",
    "extra": {
      "incidentNumber": "32403",
      "run_id": "32403",
      "address": "3700 Block Belleau Wood Drive",
      "rawType": "MED",
      "typeCode": "MED",
      "alert": "10",
      "alertType": "combinedIncident",
      "activePlatoon": "P1",
      "apparatus": "E16,EC2",
      "units": "E16,EC2",
      "unitCount": "2",
      "primaryTopic": "MED",
      "commandUnits": "",
      "dedupeKey": "INCIDENT-32403"
    }
  },
  {
    "runNumber": "32402",
    "rawCode": "MED",
    "timestamp": "2026-06-17T13:52:01.880027-04:00",
    "address": "1700 Block Jennifer Road",
    "extra": {
      "incidentNumber": "32402",
      "run_id": "32402",
      "address": "1700 Block Jennifer Road",
      "rawType": "MED",
      "typeCode": "MED",
      "alert": "10",
      "alertType": "combinedIncident",
      "activePlatoon": "P1",
      "apparatus": "255",
      "units": "255",
      "unitCount": "1",
      "primaryTopic": "MED",
      "commandUnits": "",
      "dedupeKey": "INCIDENT-32402"
    }
  },
  {
    "runNumber": "32405",
    "rawCode": "MED",
    "timestamp": "2026-06-17T13:55:55.926939-04:00",
    "address": "600 Block Old Frankfort Circle",
    "extra": {
      "incidentNumber": "32405",
      "run_id": "32405",
      "address": "600 Block Old Frankfort Circle",
      "rawType": "MED",
      "typeCode": "MED",
      "alert": "10",
      "alertType": "combinedIncident",
      "activePlatoon": "P1",
      "apparatus": "EC10",
      "units": "EC10",
      "unitCount": "1",
      "primaryTopic": "MED",
      "commandUnits": "",
      "dedupeKey": "INCIDENT-32405"
    }
  },
  {
    "runNumber": "32406",
    "rawCode": "MED",
    "timestamp": "2026-06-17T14:03:56.330193-04:00",
    "address": "700 Block Florida Street",
    "extra": {
      "incidentNumber": "32406",
      "run_id": "32406",
      "address": "700 Block Florida Street",
      "rawType": "MED",
      "typeCode": "MED",
      "alert": "10",
      "alertType": "combinedIncident",
      "activePlatoon": "P1",
      "apparatus": "RS1",
      "units": "RS1",
      "unitCount": "1",
      "primaryTopic": "MED",
      "commandUnits": "",
      "dedupeKey": "INCIDENT-32406"
    }
  },
  {
    "runNumber": "32408",
    "rawCode": "MED",
    "timestamp": "2026-06-17T14:07:57.388684-04:00",
    "address": "1500 Block Trent Boulevard",
    "extra": {
      "incidentNumber": "32408",
      "run_id": "32408",
      "address": "1500 Block Trent Boulevard",
      "rawType": "MED",
      "typeCode": "MED",
      "alert": "10",
      "alertType": "combinedIncident",
      "activePlatoon": "P1",
      "apparatus": "EC11",
      "units": "EC11",
      "unitCount": "1",
      "primaryTopic": "MED",
      "commandUnits": "",
      "dedupeKey": "INCIDENT-32408"
    }
  },
  {
    "runNumber": "32407",
    "rawCode": "MED",
    "timestamp": "2026-06-17T14:08:00.255622-04:00",
    "address": "1000 Block Tanbark Road",
    "extra": {
      "incidentNumber": "32407",
      "run_id": "32407",
      "address": "1000 Block Tanbark Road",
      "rawType": "MED",
      "typeCode": "MED",
      "alert": "10",
      "alertType": "combinedIncident",
      "activePlatoon": "P1",
      "apparatus": "EC2",
      "units": "EC2",
      "unitCount": "1",
      "primaryTopic": "MED",
      "commandUnits": "",
      "dedupeKey": "INCIDENT-32407"
    }
  },
  {
    "runNumber": "32409",
    "rawCode": "FNGL",
    "timestamp": "2026-06-17T14:16:02.602742-04:00",
    "address": "2195 Harrodsburg Road",
    "extra": {
      "incidentNumber": "32409",
      "run_id": "32409",
      "address": "2195 Harrodsburg Road",
      "rawType": "FNGL",
      "typeCode": "FNGL",
      "alert": "10",
      "alertType": "combinedIncident",
      "activePlatoon": "P1",
      "apparatus": "FIRE2,E11,E20,L04,EC7,204,220",
      "units": "FIRE2,E11,E20,L04,EC7,204,220",
      "unitCount": "7",
      "primaryTopic": "FNGL",
      "commandUnits": "220,204",
      "dedupeKey": "INCIDENT-32409"
    }
  },
  {
    "runNumber": "32410",
    "rawCode": "MED",
    "timestamp": "2026-06-17T14:24:02.077421-04:00",
    "address": "Man O War Boulevard & Palumbo Drive",
    "extra": {
      "incidentNumber": "32410",
      "run_id": "32410",
      "address": "Man O War Boulevard & Palumbo Drive",
      "rawType": "MED",
      "typeCode": "MED",
      "alert": "10",
      "alertType": "combinedIncident",
      "activePlatoon": "P1",
      "apparatus": "E21",
      "units": "E21",
      "unitCount": "1",
      "primaryTopic": "MED",
      "commandUnits": "",
      "dedupeKey": "INCIDENT-32410"
    }
  },
  {
    "runNumber": "32411",
    "rawCode": "MED",
    "timestamp": "2026-06-17T14:32:01.450713-04:00",
    "address": "0 Block Imperial Avenue",
    "extra": {
      "incidentNumber": "32411",
      "run_id": "32411",
      "address": "0 Block Imperial Avenue",
      "rawType": "MED",
      "typeCode": "MED",
      "alert": "10",
      "alertType": "combinedIncident",
      "activePlatoon": "P1",
      "apparatus": "EC1",
      "units": "EC1",
      "unitCount": "1",
      "primaryTopic": "MED",
      "commandUnits": "",
      "dedupeKey": "INCIDENT-32411"
    }
  },
  {
    "runNumber": "32412",
    "rawCode": "MED",
    "timestamp": "2026-06-17T14:40:01.276299-04:00",
    "address": "200 Block Mechanic Street",
    "extra": {
      "incidentNumber": "32412",
      "run_id": "32412",
      "address": "200 Block Mechanic Street",
      "rawType": "MED",
      "typeCode": "MED",
      "alert": "10",
      "alertType": "combinedIncident",
      "activePlatoon": "P1",
      "apparatus": "EC10",
      "units": "EC10",
      "unitCount": "1",
      "primaryTopic": "MED",
      "commandUnits": "",
      "dedupeKey": "INCIDENT-32412"
    }
  },
  {
    "runNumber": "32413",
    "rawCode": "MED",
    "timestamp": "2026-06-17T14:44:01.503887-04:00",
    "address": "500 Block Eureka Springs Drive",
    "extra": {
      "incidentNumber": "32413",
      "run_id": "32413",
      "address": "500 Block Eureka Springs Drive",
      "rawType": "MED",
      "typeCode": "MED",
      "alert": "10",
      "alertType": "combinedIncident",
      "activePlatoon": "P1",
      "apparatus": "EC13",
      "units": "EC13",
      "unitCount": "1",
      "primaryTopic": "MED",
      "commandUnits": "",
      "dedupeKey": "INCIDENT-32413"
    }
  },
  {
    "runNumber": "32417",
    "rawCode": "MED",
    "timestamp": "2026-06-17T14:48:02.440371-04:00",
    "address": "3400 Block Buckhorn Drive",
    "extra": {
      "incidentNumber": "32417",
      "run_id": "32417",
      "address": "3400 Block Buckhorn Drive",
      "rawType": "MED",
      "typeCode": "MED",
      "alert": "10",
      "alertType": "combinedIncident",
      "activePlatoon": "P1",
      "apparatus": "E16",
      "units": "E16",
      "unitCount": "1",
      "primaryTopic": "MED",
      "commandUnits": "",
      "dedupeKey": "INCIDENT-32417"
    }
  },
  {
    "runNumber": "32416",
    "rawCode": "MED",
    "timestamp": "2026-06-17T14:48:04.742660-04:00",
    "address": "200 Block E Reynolds Road",
    "extra": {
      "incidentNumber": "32416",
      "run_id": "32416",
      "address": "200 Block E Reynolds Road",
      "rawType": "MED",
      "typeCode": "MED",
      "alert": "10",
      "alertType": "combinedIncident",
      "activePlatoon": "P1",
      "apparatus": "E15",
      "units": "E15",
      "unitCount": "1",
      "primaryTopic": "MED",
      "commandUnits": "",
      "dedupeKey": "INCIDENT-32416"
    }
  },
  {
    "runNumber": "32415",
    "rawCode": "MED",
    "timestamp": "2026-06-17T14:48:07.081013-04:00",
    "address": "3100 Block Mapleleaf Drive",
    "extra": {
      "incidentNumber": "32415",
      "run_id": "32415",
      "address": "3100 Block Mapleleaf Drive",
      "rawType": "MED",
      "typeCode": "MED",
      "alert": "10",
      "alertType": "combinedIncident",
      "activePlatoon": "P1",
      "apparatus": "E21,EC12",
      "units": "E21,EC12",
      "unitCount": "2",
      "primaryTopic": "MED",
      "commandUnits": "",
      "dedupeKey": "INCIDENT-32415"
    }
  },
  {
    "runNumber": "32414",
    "rawCode": "MED",
    "timestamp": "2026-06-17T14:48:10.021760-04:00",
    "address": "200 Block Twin Shores Court",
    "extra": {
      "incidentNumber": "32414",
      "run_id": "32414",
      "address": "200 Block Twin Shores Court",
      "rawType": "MED",
      "typeCode": "MED",
      "alert": "10",
      "alertType": "combinedIncident",
      "activePlatoon": "P1",
      "apparatus": "E09,EC9",
      "units": "E09,EC9",
      "unitCount": "2",
      "primaryTopic": "MED",
      "commandUnits": "",
      "dedupeKey": "INCIDENT-32414"
    }
  },
  {
    "runNumber": "32418",
    "rawCode": "MED",
    "timestamp": "2026-06-17T14:52:03.459249-04:00",
    "address": "500 Block W Second Street",
    "extra": {
      "incidentNumber": "32418",
      "run_id": "32418",
      "address": "500 Block W Second Street",
      "rawType": "MED",
      "typeCode": "MED",
      "alert": "10",
      "alertType": "combinedIncident",
      "activePlatoon": "P1",
      "apparatus": "E04",
      "units": "E04",
      "unitCount": "1",
      "primaryTopic": "MED",
      "commandUnits": "",
      "dedupeKey": "INCIDENT-32418"
    }
  },
  {
    "runNumber": "32420",
    "rawCode": "FVEA",
    "timestamp": "2026-06-17T14:56:04.996511-04:00",
    "address": "W Third Street & Hampton Court",
    "extra": {
      "incidentNumber": "32420",
      "run_id": "32420",
      "address": "W Third Street & Hampton Court",
      "rawType": "FVEA",
      "typeCode": "FVEA",
      "alert": "10",
      "alertType": "combinedIncident",
      "activePlatoon": "P1",
      "apparatus": "RS1",
      "units": "RS1",
      "unitCount": "1",
      "primaryTopic": "FVEA",
      "commandUnits": "",
      "dedupeKey": "INCIDENT-32420"
    }
  },
  {
    "runNumber": "32419",
    "rawCode": "MED",
    "timestamp": "2026-06-17T14:56:07.187496-04:00",
    "address": "500 Block W Second Street",
    "extra": {
      "incidentNumber": "32419",
      "run_id": "32419",
      "address": "500 Block W Second Street",
      "rawType": "MED",
      "typeCode": "MED",
      "alert": "10",
      "alertType": "combinedIncident",
      "activePlatoon": "P1",
      "apparatus": "L01",
      "units": "L01",
      "unitCount": "1",
      "primaryTopic": "MED",
      "commandUnits": "",
      "dedupeKey": "INCIDENT-32419"
    }
  },
  {
    "runNumber": "32421",
    "rawCode": "FMEA",
    "timestamp": "2026-06-17T15:08:05.078359-04:00",
    "address": "1230 Todds Station",
    "extra": {
      "incidentNumber": "32421",
      "run_id": "32421",
      "address": "1230 Todds Station",
      "rawType": "FMEA",
      "typeCode": "FMEA",
      "alert": "10",
      "alertType": "combinedIncident",
      "activePlatoon": "P1",
      "apparatus": "E21",
      "units": "E21",
      "unitCount": "1",
      "primaryTopic": "FMEA",
      "commandUnits": "",
      "dedupeKey": "INCIDENT-32421"
    }
  },
  {
    "runNumber": "32422",
    "rawCode": "MED",
    "timestamp": "2026-06-17T15:12:06.226828-04:00",
    "address": "3300 Block Cheltenham Drive",
    "extra": {
      "incidentNumber": "32422",
      "run_id": "32422",
      "address": "3300 Block Cheltenham Drive",
      "rawType": "MED",
      "typeCode": "MED",
      "alert": "10",
      "alertType": "combinedIncident",
      "activePlatoon": "P1",
      "apparatus": "L06",
      "units": "L06",
      "unitCount": "1",
      "primaryTopic": "MED",
      "commandUnits": "",
      "dedupeKey": "INCIDENT-32422"
    }
  },
  {
    "runNumber": "32424",
    "rawCode": "MED",
    "timestamp": "2026-06-17T15:20:07.008487-04:00",
    "address": "1600 Block Alexandria Drive",
    "extra": {
      "incidentNumber": "32424",
      "run_id": "32424",
      "address": "1600 Block Alexandria Drive",
      "rawType": "MED",
      "typeCode": "MED",
      "alert": "10",
      "alertType": "combinedIncident",
      "activePlatoon": "P1",
      "apparatus": "E20",
      "units": "E20",
      "unitCount": "1",
      "primaryTopic": "MED",
      "commandUnits": "",
      "dedupeKey": "INCIDENT-32424"
    }
  },
  {
    "runNumber": "32423",
    "rawCode": "FVEA",
    "timestamp": "2026-06-17T15:20:09.698207-04:00",
    "address": "Kilkenny Drive & Arundel Drive",
    "extra": {
      "incidentNumber": "32423",
      "run_id": "32423",
      "address": "Kilkenny Drive & Arundel Drive",
      "rawType": "FVEA",
      "typeCode": "FVEA",
      "alert": "10",
      "alertType": "combinedIncident",
      "activePlatoon": "P1",
      "apparatus": "E02",
      "units": "E02",
      "unitCount": "1",
      "primaryTopic": "FVEA",
      "commandUnits": "",
      "dedupeKey": "INCIDENT-32423"
    }
  },
  {
    "runNumber": "32425",
    "rawCode": "FPRT",
    "timestamp": "2026-06-17T15:36:09.359403-04:00",
    "address": "4270 Georgetown Road",
    "extra": {
      "incidentNumber": "32425",
      "run_id": "32425",
      "address": "4270 Georgetown Road",
      "rawType": "FPRT",
      "typeCode": "FPRT",
      "alert": "10",
      "alertType": "combinedIncident",
      "activePlatoon": "P1",
      "apparatus": "FIRE1,E08,E12,L01,205",
      "units": "FIRE1,E08,E12,L01,205",
      "unitCount": "5",
      "primaryTopic": "FPRT",
      "commandUnits": "205",
      "dedupeKey": "INCIDENT-32425"
    }
  },
  {
    "runNumber": "32427",
    "rawCode": "FDUM",
    "timestamp": "2026-06-17T15:48:08.311872-04:00",
    "address": "6411 Polo Club Lane",
    "extra": {
      "incidentNumber": "32427",
      "run_id": "32427",
      "address": "6411 Polo Club Lane",
      "rawType": "FDUM",
      "typeCode": "FDUM",
      "alert": "10",
      "alertType": "combinedIncident",
      "activePlatoon": "P1",
      "apparatus": "E21",
      "units": "E21",
      "unitCount": "1",
      "primaryTopic": "FDUM",
      "commandUnits": "",
      "dedupeKey": "INCIDENT-32427"
    }
  },
  {
    "runNumber": "32426",
    "rawCode": "MED",
    "timestamp": "2026-06-17T15:48:10.483097-04:00",
    "address": "2500 Block Southview Drive",
    "extra": {
      "incidentNumber": "32426",
      "run_id": "32426",
      "address": "2500 Block Southview Drive",
      "rawType": "MED",
      "typeCode": "MED",
      "alert": "10",
      "alertType": "combinedIncident",
      "activePlatoon": "P1",
      "apparatus": "EC9",
      "units": "EC9",
      "unitCount": "1",
      "primaryTopic": "MED",
      "commandUnits": "",
      "dedupeKey": "INCIDENT-32426"
    }
  },
  {
    "runNumber": "32429",
    "rawCode": "MED",
    "timestamp": "2026-06-17T16:00:12.387478-04:00",
    "address": "2800 Block Ark Royal Way",
    "extra": {
      "incidentNumber": "32429",
      "run_id": "32429",
      "address": "2800 Block Ark Royal Way",
      "rawType": "MED",
      "typeCode": "MED",
      "alert": "10",
      "alertType": "combinedIncident",
      "activePlatoon": "P1",
      "apparatus": "EC7,CRT1",
      "units": "EC7,CRT1",
      "unitCount": "2",
      "primaryTopic": "MED",
      "commandUnits": "",
      "dedupeKey": "INCIDENT-32429"
    }
  },
  {
    "runNumber": "32428",
    "rawCode": "MED",
    "timestamp": "2026-06-17T16:00:15.611075-04:00",
    "address": "4600 Block Riverman Way",
    "extra": {
      "incidentNumber": "32428",
      "run_id": "32428",
      "address": "4600 Block Riverman Way",
      "rawType": "MED",
      "typeCode": "MED",
      "alert": "10",
      "alertType": "combinedIncident",
      "activePlatoon": "P1",
      "apparatus": "E22,EC4",
      "units": "E22,EC4",
      "unitCount": "2",
      "primaryTopic": "MED",
      "commandUnits": "",
      "dedupeKey": "INCIDENT-32428"
    }
  },
  {
    "runNumber": "32430",
    "rawCode": "MED",
    "timestamp": "2026-06-17T16:24:12.692135-04:00",
    "address": "100 Block E Main Street",
    "extra": {
      "incidentNumber": "32430",
      "run_id": "32430",
      "address": "100 Block E Main Street",
      "rawType": "MED",
      "typeCode": "MED",
      "alert": "10",
      "alertType": "combinedIncident",
      "activePlatoon": "P1",
      "apparatus": "EC1",
      "units": "EC1",
      "unitCount": "1",
      "primaryTopic": "MED",
      "commandUnits": "",
      "dedupeKey": "INCIDENT-32430"
    }
  },
  {
    "runNumber": "32432",
    "rawCode": "MED",
    "timestamp": "2026-06-17T16:32:14.835928-04:00",
    "address": "1500 Block Trent Boulevard",
    "extra": {
      "incidentNumber": "32432",
      "run_id": "32432",
      "address": "1500 Block Trent Boulevard",
      "rawType": "MED",
      "typeCode": "MED",
      "alert": "10",
      "alertType": "combinedIncident",
      "activePlatoon": "P1",
      "apparatus": "EC13",
      "units": "EC13",
      "unitCount": "1",
      "primaryTopic": "MED",
      "commandUnits": "",
      "dedupeKey": "INCIDENT-32432"
    }
  },
  {
    "runNumber": "32431",
    "rawCode": "MED",
    "timestamp": "2026-06-17T16:32:17.331244-04:00",
    "address": "700 Block Vicki Way",
    "extra": {
      "incidentNumber": "32431",
      "run_id": "32431",
      "address": "700 Block Vicki Way",
      "rawType": "MED",
      "typeCode": "MED",
      "alert": "10",
      "alertType": "combinedIncident",
      "activePlatoon": "P1",
      "apparatus": "EC8",
      "units": "EC8",
      "unitCount": "1",
      "primaryTopic": "MED",
      "commandUnits": "",
      "dedupeKey": "INCIDENT-32431"
    }
  },
  {
    "runNumber": "32433",
    "rawCode": "MED",
    "timestamp": "2026-06-17T16:36:16.058299-04:00",
    "address": "300 Block Newtown Pike",
    "extra": {
      "incidentNumber": "32433",
      "run_id": "32433",
      "address": "300 Block Newtown Pike",
      "rawType": "MED",
      "typeCode": "MED",
      "alert": "10",
      "alertType": "combinedIncident",
      "activePlatoon": "P1",
      "apparatus": "EC6",
      "units": "EC6",
      "unitCount": "1",
      "primaryTopic": "MED",
      "commandUnits": "",
      "dedupeKey": "INCIDENT-32433"
    }
  },
  {
    "runNumber": "32434",
    "rawCode": "MED",
    "timestamp": "2026-06-17T16:40:16.107461-04:00",
    "address": "1400 Block Coleman Court",
    "extra": {
      "incidentNumber": "32434",
      "run_id": "32434",
      "address": "1400 Block Coleman Court",
      "rawType": "MED",
      "typeCode": "MED",
      "alert": "10",
      "alertType": "combinedIncident",
      "activePlatoon": "P1",
      "apparatus": "E19,EC3",
      "units": "E19,EC3",
      "unitCount": "2",
      "primaryTopic": "MED",
      "commandUnits": "",
      "dedupeKey": "INCIDENT-32434"
    }
  },
  {
    "runNumber": "32435",
    "rawCode": "MED",
    "timestamp": "2026-06-17T16:44:16.704940-04:00",
    "address": "2100 Block Nicholasville Road",
    "extra": {
      "incidentNumber": "32435",
      "run_id": "32435",
      "address": "2100 Block Nicholasville Road",
      "rawType": "MED",
      "typeCode": "MED",
      "alert": "10",
      "alertType": "combinedIncident",
      "activePlatoon": "P1",
      "apparatus": "EC12",
      "units": "EC12",
      "unitCount": "1",
      "primaryTopic": "MED",
      "commandUnits": "",
      "dedupeKey": "INCIDENT-32435"
    }
  },
  {
    "runNumber": "32436",
    "rawCode": "MED",
    "timestamp": "2026-06-17T17:04:20.058027-04:00",
    "address": "3400 Block Crimson King Court",
    "extra": {
      "incidentNumber": "32436",
      "run_id": "32436",
      "address": "3400 Block Crimson King Court",
      "rawType": "MED",
      "typeCode": "MED",
      "alert": "10",
      "alertType": "combinedIncident",
      "activePlatoon": "P1",
      "apparatus": "E16,EC4",
      "units": "E16,EC4",
      "unitCount": "2",
      "primaryTopic": "MED",
      "commandUnits": "",
      "dedupeKey": "INCIDENT-32436"
    }
  },
  {
    "runNumber": "32438",
    "rawCode": "MED",
    "timestamp": "2026-06-17T17:16:21.266406-04:00",
    "address": "1800 Block Augusta Court",
    "extra": {
      "incidentNumber": "32438",
      "run_id": "32438",
      "address": "1800 Block Augusta Court",
      "rawType": "MED",
      "typeCode": "MED",
      "alert": "10",
      "alertType": "combinedIncident",
      "activePlatoon": "P1",
      "apparatus": "E02,EC2,241",
      "units": "E02,EC2,241",
      "unitCount": "3",
      "primaryTopic": "MED",
      "commandUnits": "241",
      "dedupeKey": "INCIDENT-32438"
    }
  },
  {
    "runNumber": "32437",
    "rawCode": "FLIFT",
    "timestamp": "2026-06-17T17:16:24.997962-04:00",
    "address": "115 Garrett Avenue",
    "extra": {
      "incidentNumber": "32437",
      "run_id": "32437",
      "address": "115 Garrett Avenue",
      "rawType": "FLIFT",
      "typeCode": "FLIFT",
      "alert": "10",
      "alertType": "combinedIncident",
      "activePlatoon": "P1",
      "apparatus": "E14",
      "units": "E14",
      "unitCount": "1",
      "primaryTopic": "FLIFT",
      "commandUnits": "",
      "dedupeKey": "INCIDENT-32437"
    }
  },
  {
    "runNumber": "32439",
    "rawCode": "MED",
    "timestamp": "2026-06-17T17:32:20.719256-04:00",
    "address": "3900 Block Weber Way",
    "extra": {
      "incidentNumber": "32439",
      "run_id": "32439",
      "address": "3900 Block Weber Way",
      "rawType": "MED",
      "typeCode": "MED",
      "alert": "10",
      "alertType": "combinedIncident",
      "activePlatoon": "P1",
      "apparatus": "EC9",
      "units": "EC9",
      "unitCount": "1",
      "primaryTopic": "MED",
      "commandUnits": "",
      "dedupeKey": "INCIDENT-32439"
    }
  },
  {
    "runNumber": "32440",
    "rawCode": "MED",
    "timestamp": "2026-06-17T17:48:24.823455-04:00",
    "address": "600 Block Rosewood Drive",
    "extra": {
      "incidentNumber": "32440",
      "run_id": "32440",
      "address": "600 Block Rosewood Drive",
      "rawType": "MED",
      "typeCode": "MED",
      "alert": "10",
      "alertType": "combinedIncident",
      "activePlatoon": "P1",
      "apparatus": "EC3",
      "units": "EC3",
      "unitCount": "1",
      "primaryTopic": "MED",
      "commandUnits": "",
      "dedupeKey": "INCIDENT-32440"
    }
  },
  {
    "runNumber": "32442",
    "rawCode": "MED",
    "timestamp": "2026-06-17T17:52:24.421945-04:00",
    "address": "200 Block E Vine Street",
    "extra": {
      "incidentNumber": "32442",
      "run_id": "32442",
      "address": "200 Block E Vine Street",
      "rawType": "MED",
      "typeCode": "MED",
      "alert": "10",
      "alertType": "combinedIncident",
      "activePlatoon": "P1",
      "apparatus": "EC10",
      "units": "EC10",
      "unitCount": "1",
      "primaryTopic": "MED",
      "commandUnits": "",
      "dedupeKey": "INCIDENT-32442"
    }
  },
  {
    "runNumber": "32441",
    "rawCode": "MED",
    "timestamp": "2026-06-17T17:52:26.670565-04:00",
    "address": "Elm Tree Lane & Corral Street",
    "extra": {
      "incidentNumber": "32441",
      "run_id": "32441",
      "address": "Elm Tree Lane & Corral Street",
      "rawType": "MED",
      "typeCode": "MED",
      "alert": "10",
      "alertType": "combinedIncident",
      "activePlatoon": "P1",
      "apparatus": "E01,EC1",
      "units": "E01,EC1",
      "unitCount": "2",
      "primaryTopic": "MED",
      "commandUnits": "",
      "dedupeKey": "INCIDENT-32441"
    }
  },
  {
    "runNumber": "32445",
    "rawCode": "MED",
    "timestamp": "2026-06-17T18:04:24.019513-04:00",
    "address": "300 Block Newtown Pike",
    "extra": {
      "incidentNumber": "32445",
      "run_id": "32445",
      "address": "300 Block Newtown Pike",
      "rawType": "MED",
      "typeCode": "MED",
      "alert": "10",
      "alertType": "combinedIncident",
      "activePlatoon": "P1",
      "apparatus": "EC6",
      "units": "EC6",
      "unitCount": "1",
      "primaryTopic": "MED",
      "commandUnits": "",
      "dedupeKey": "INCIDENT-32445"
    }
  },
  {
    "runNumber": "32444",
    "rawCode": "MED",
    "timestamp": "2026-06-17T18:04:26.569105-04:00",
    "address": "S Ashland Avenue & E High Street",
    "extra": {
      "incidentNumber": "32444",
      "run_id": "32444",
      "address": "S Ashland Avenue & E High Street",
      "rawType": "MED",
      "typeCode": "MED",
      "alert": "10",
      "alertType": "combinedIncident",
      "activePlatoon": "P1",
      "apparatus": "E05,EC2",
      "units": "E05,EC2",
      "unitCount": "2",
      "primaryTopic": "MED",
      "commandUnits": "",
      "dedupeKey": "INCIDENT-32444"
    }
  },
  {
    "runNumber": "32443",
    "rawCode": "MED",
    "timestamp": "2026-06-17T18:04:29.446305-04:00",
    "address": "100 Block E Main Street",
    "extra": {
      "incidentNumber": "32443",
      "run_id": "32443",
      "address": "100 Block E Main Street",
      "rawType": "MED",
      "typeCode": "MED",
      "alert": "10",
      "alertType": "combinedIncident",
      "activePlatoon": "P1",
      "apparatus": "EC7",
      "units": "EC7",
      "unitCount": "1",
      "primaryTopic": "MED",
      "commandUnits": "",
      "dedupeKey": "INCIDENT-32443"
    }
  },
  {
    "runNumber": "32446",
    "rawCode": "MED",
    "timestamp": "2026-06-17T18:08:25.405795-04:00",
    "address": "2200 Block Winterberry Drive",
    "extra": {
      "incidentNumber": "32446",
      "run_id": "32446",
      "address": "2200 Block Winterberry Drive",
      "rawType": "MED",
      "typeCode": "MED",
      "alert": "10",
      "alertType": "combinedIncident",
      "activePlatoon": "P1",
      "apparatus": "EC5",
      "units": "EC5",
      "unitCount": "1",
      "primaryTopic": "MED",
      "commandUnits": "",
      "dedupeKey": "INCIDENT-32446"
    }
  },
  {
    "runNumber": "32448",
    "rawCode": "MED",
    "timestamp": "2026-06-17T18:16:28.154703-04:00",
    "address": "400 Block Northridge Drive",
    "extra": {
      "incidentNumber": "32448",
      "run_id": "32448",
      "address": "400 Block Northridge Drive",
      "rawType": "MED",
      "typeCode": "MED",
      "alert": "10",
      "alertType": "combinedIncident",
      "activePlatoon": "P1",
      "apparatus": "EC8",
      "units": "EC8",
      "unitCount": "1",
      "primaryTopic": "MED",
      "commandUnits": "",
      "dedupeKey": "INCIDENT-32448"
    }
  },
  {
    "runNumber": "32447",
    "rawCode": "MED",
    "timestamp": "2026-06-17T18:16:30.422457-04:00",
    "address": "400 Block Severn Way",
    "extra": {
      "incidentNumber": "32447",
      "run_id": "32447",
      "address": "400 Block Severn Way",
      "rawType": "MED",
      "typeCode": "MED",
      "alert": "10",
      "alertType": "combinedIncident",
      "activePlatoon": "P1",
      "apparatus": "E12,EC4",
      "units": "E12,EC4",
      "unitCount": "2",
      "primaryTopic": "MED",
      "commandUnits": "",
      "dedupeKey": "INCIDENT-32447"
    }
  },
  {
    "runNumber": "32449",
    "rawCode": "FVEA",
    "timestamp": "2026-06-17T18:24:29.463740-04:00",
    "address": "110 Transcript Avenue",
    "extra": {
      "incidentNumber": "32449",
      "run_id": "32449",
      "address": "110 Transcript Avenue",
      "rawType": "FVEA",
      "typeCode": "FVEA",
      "alert": "10",
      "alertType": "combinedIncident",
      "activePlatoon": "P1",
      "apparatus": "E06,EC12",
      "units": "E06,EC12",
      "unitCount": "2",
      "primaryTopic": "FVEA",
      "commandUnits": "",
      "dedupeKey": "INCIDENT-32449"
    }
  },
  {
    "runNumber": "32450",
    "rawCode": "MED",
    "timestamp": "2026-06-17T18:32:29.188286-04:00",
    "address": "600 Block Charlbury Road",
    "extra": {
      "incidentNumber": "32450",
      "run_id": "32450",
      "address": "600 Block Charlbury Road",
      "rawType": "MED",
      "typeCode": "MED",
      "alert": "10",
      "alertType": "combinedIncident",
      "activePlatoon": "P1",
      "apparatus": "E08,EC1,CRT1",
      "units": "E08,EC1,CRT1",
      "unitCount": "3",
      "primaryTopic": "MED",
      "commandUnits": "",
      "dedupeKey": "INCIDENT-32450"
    }
  },
  {
    "runNumber": "32451",
    "rawCode": "FPRT",
    "timestamp": "2026-06-17T18:40:30.590865-04:00",
    "address": "217 Owsley Avenue",
    "extra": {
      "incidentNumber": "32451",
      "run_id": "32451",
      "address": "217 Owsley Avenue",
      "rawType": "FPRT",
      "typeCode": "FPRT",
      "alert": "10",
      "alertType": "combinedIncident",
      "activePlatoon": "P1",
      "apparatus": "FIRE1,E05,E09,L02,205",
      "units": "FIRE1,E05,E09,L02,205",
      "unitCount": "5",
      "primaryTopic": "FPRT",
      "commandUnits": "205",
      "dedupeKey": "INCIDENT-32451"
    }
  },
  {
    "runNumber": "32452",
    "rawCode": "MED",
    "timestamp": "2026-06-17T18:44:30.442801-04:00",
    "address": "100 Block Larue",
    "extra": {
      "incidentNumber": "32452",
      "run_id": "32452",
      "address": "100 Block Larue",
      "rawType": "MED",
      "typeCode": "MED",
      "alert": "10",
      "alertType": "combinedIncident",
      "activePlatoon": "P1",
      "apparatus": "E15,EC9",
      "units": "E15,EC9",
      "unitCount": "2",
      "primaryTopic": "MED",
      "commandUnits": "",
      "dedupeKey": "INCIDENT-32452"
    }
  },
  {
    "runNumber": "32455",
    "rawCode": "MED",
    "timestamp": "2026-06-17T18:48:31.850009-04:00",
    "address": "3100 Block Pimlico Parkway",
    "extra": {
      "incidentNumber": "32455",
      "run_id": "32455",
      "address": "3100 Block Pimlico Parkway",
      "rawType": "MED",
      "typeCode": "MED",
      "alert": "10",
      "alertType": "combinedIncident",
      "activePlatoon": "P1",
      "apparatus": "EC13",
      "units": "EC13",
      "unitCount": "1",
      "primaryTopic": "MED",
      "commandUnits": "",
      "dedupeKey": "INCIDENT-32455"
    }
  },
  {
    "runNumber": "32454",
    "rawCode": "MED",
    "timestamp": "2026-06-17T18:48:34.250742-04:00",
    "address": "800 Block E Loudon Avenue",
    "extra": {
      "incidentNumber": "32454",
      "run_id": "32454",
      "address": "800 Block E Loudon Avenue",
      "rawType": "MED",
      "typeCode": "MED",
      "alert": "10",
      "alertType": "combinedIncident",
      "activePlatoon": "P1",
      "apparatus": "L05,EC3",
      "units": "L05,EC3",
      "unitCount": "2",
      "primaryTopic": "MED",
      "commandUnits": "",
      "dedupeKey": "INCIDENT-32454"
    }
  },
  {
    "runNumber": "32453",
    "rawCode": "MED",
    "timestamp": "2026-06-17T18:48:37.026646-04:00",
    "address": "800 Block E Loudon Avenue",
    "extra": {
      "incidentNumber": "32453",
      "run_id": "32453",
      "address": "800 Block E Loudon Avenue",
      "rawType": "MED",
      "typeCode": "MED",
      "alert": "10",
      "alertType": "combinedIncident",
      "activePlatoon": "P1",
      "apparatus": "E02,EC1",
      "units": "E02,EC1",
      "unitCount": "2",
      "primaryTopic": "MED",
      "commandUnits": "",
      "dedupeKey": "INCIDENT-32453"
    }
  },
  {
    "runNumber": "32457",
    "rawCode": "MED",
    "timestamp": "2026-06-17T18:56:33.699036-04:00",
    "address": "N Martin Luther King Boulevard & E",
    "extra": {
      "incidentNumber": "32457",
      "run_id": "32457",
      "address": "N Martin Luther King Boulevard & E",
      "rawType": "MED",
      "typeCode": "MED",
      "alert": "10",
      "alertType": "combinedIncident",
      "activePlatoon": "P1",
      "apparatus": "E01",
      "units": "E01",
      "unitCount": "1",
      "primaryTopic": "MED",
      "commandUnits": "",
      "dedupeKey": "INCIDENT-32457"
    }
  },
  {
    "runNumber": "32456",
    "rawCode": "MED",
    "timestamp": "2026-06-17T18:56:35.966732-04:00",
    "address": "1000 Block Georgetown Road",
    "extra": {
      "incidentNumber": "32456",
      "run_id": "32456",
      "address": "1000 Block Georgetown Road",
      "rawType": "MED",
      "typeCode": "MED",
      "alert": "10",
      "alertType": "combinedIncident",
      "activePlatoon": "P1",
      "apparatus": "E10,EC6",
      "units": "E10,EC6",
      "unitCount": "2",
      "primaryTopic": "MED",
      "commandUnits": "",
      "dedupeKey": "INCIDENT-32456"
    }
  },
  {
    "runNumber": "32458",
    "rawCode": "MED",
    "timestamp": "2026-06-17T19:20:35.408119-04:00",
    "address": "3100 Block Custer Drive",
    "extra": {
      "incidentNumber": "32458",
      "run_id": "32458",
      "address": "3100 Block Custer Drive",
      "rawType": "MED",
      "typeCode": "MED",
      "alert": "10",
      "alertType": "combinedIncident",
      "activePlatoon": "P1",
      "apparatus": "E16",
      "units": "E16",
      "unitCount": "1",
      "primaryTopic": "MED",
      "commandUnits": "",
      "dedupeKey": "INCIDENT-32458"
    }
  },
  {
    "runNumber": "32459",
    "rawCode": "MED",
    "timestamp": "2026-06-17T19:40:38.293135-04:00",
    "address": "3300 Block Tates Creek Road",
    "extra": {
      "incidentNumber": "32459",
      "run_id": "32459",
      "address": "3300 Block Tates Creek Road",
      "rawType": "MED",
      "typeCode": "MED",
      "alert": "10",
      "alertType": "combinedIncident",
      "activePlatoon": "P1",
      "apparatus": "EC4",
      "units": "EC4",
      "unitCount": "1",
      "primaryTopic": "MED",
      "commandUnits": "",
      "dedupeKey": "INCIDENT-32459"
    }
  },
  {
    "runNumber": "32461",
    "rawCode": "MED",
    "timestamp": "2026-06-17T19:44:37.162547-04:00",
    "address": "5700 Block Briar Hill Road",
    "extra": {
      "incidentNumber": "32461",
      "run_id": "32461",
      "address": "5700 Block Briar Hill Road",
      "rawType": "MED",
      "typeCode": "MED",
      "alert": "10",
      "alertType": "combinedIncident",
      "activePlatoon": "P1",
      "apparatus": "E23,EC8",
      "units": "E23,EC8",
      "unitCount": "2",
      "primaryTopic": "MED",
      "commandUnits": "",
      "dedupeKey": "INCIDENT-32461"
    }
  },
  {
    "runNumber": "32460",
    "rawCode": "MED",
    "timestamp": "2026-06-17T19:44:40.622973-04:00",
    "address": "300 Block Park View Avenue",
    "extra": {
      "incidentNumber": "32460",
      "run_id": "32460",
      "address": "300 Block Park View Avenue",
      "rawType": "MED",
      "typeCode": "MED",
      "alert": "10",
      "alertType": "combinedIncident",
      "activePlatoon": "P1",
      "apparatus": "E08,EC3",
      "units": "E08,EC3",
      "unitCount": "2",
      "primaryTopic": "MED",
      "commandUnits": "",
      "dedupeKey": "INCIDENT-32460"
    }
  },
  {
    "runNumber": "32462",
    "rawCode": "MED",
    "timestamp": "2026-06-17T19:56:38.849411-04:00",
    "address": "3100 Block Rio Dosa Drive",
    "extra": {
      "incidentNumber": "32462",
      "run_id": "32462",
      "address": "3100 Block Rio Dosa Drive",
      "rawType": "MED",
      "typeCode": "MED",
      "alert": "10",
      "alertType": "combinedIncident",
      "activePlatoon": "P1",
      "apparatus": "EC11",
      "units": "EC11",
      "unitCount": "1",
      "primaryTopic": "MED",
      "commandUnits": "",
      "dedupeKey": "INCIDENT-32462"
    }
  },
  {
    "runNumber": "32463",
    "rawCode": "MED",
    "timestamp": "2026-06-17T20:00:39.732601-04:00",
    "address": "1100 Block Beaumont Centre Lane",
    "extra": {
      "incidentNumber": "32463",
      "run_id": "32463",
      "address": "1100 Block Beaumont Centre Lane",
      "rawType": "MED",
      "typeCode": "MED",
      "alert": "10",
      "alertType": "combinedIncident",
      "activePlatoon": "P1",
      "apparatus": "EC12",
      "units": "EC12",
      "unitCount": "1",
      "primaryTopic": "MED",
      "commandUnits": "",
      "dedupeKey": "INCIDENT-32463"
    }
  },
  {
    "runNumber": "32465",
    "rawCode": "MED",
    "timestamp": "2026-06-17T20:08:40.860747-04:00",
    "address": "2700 Block Richmond Road",
    "extra": {
      "incidentNumber": "32465",
      "run_id": "32465",
      "address": "2700 Block Richmond Road",
      "rawType": "MED",
      "typeCode": "MED",
      "alert": "10",
      "alertType": "combinedIncident",
      "activePlatoon": "P1",
      "apparatus": "E09,EC2",
      "units": "E09,EC2",
      "unitCount": "2",
      "primaryTopic": "MED",
      "commandUnits": "",
      "dedupeKey": "INCIDENT-32465"
    }
  },
  {
    "runNumber": "32464",
    "rawCode": "MED",
    "timestamp": "2026-06-17T20:08:43.884885-04:00",
    "address": "300 Block W Loudon Avenue",
    "extra": {
      "incidentNumber": "32464",
      "run_id": "32464",
      "address": "300 Block W Loudon Avenue",
      "rawType": "MED",
      "typeCode": "MED",
      "alert": "10",
      "alertType": "combinedIncident",
      "activePlatoon": "P1",
      "apparatus": "EC3",
      "units": "EC3",
      "unitCount": "1",
      "primaryTopic": "MED",
      "commandUnits": "",
      "dedupeKey": "INCIDENT-32464"
    }
  },
  {
    "runNumber": "32466",
    "rawCode": "FLIFT",
    "timestamp": "2026-06-17T20:12:41.074020-04:00",
    "address": "501 Green Valley Drive",
    "extra": {
      "incidentNumber": "32466",
      "run_id": "32466",
      "address": "501 Green Valley Drive",
      "rawType": "FLIFT",
      "typeCode": "FLIFT",
      "alert": "10",
      "alertType": "combinedIncident",
      "activePlatoon": "P1",
      "apparatus": "E24",
      "units": "E24",
      "unitCount": "1",
      "primaryTopic": "FLIFT",
      "commandUnits": "",
      "dedupeKey": "INCIDENT-32466"
    }
  },
  {
    "runNumber": "32467",
    "rawCode": "MED",
    "timestamp": "2026-06-17T20:16:41.133159-04:00",
    "address": "100 Block Deweese Street",
    "extra": {
      "incidentNumber": "32467",
      "run_id": "32467",
      "address": "100 Block Deweese Street",
      "rawType": "MED",
      "typeCode": "MED",
      "alert": "10",
      "alertType": "combinedIncident",
      "activePlatoon": "P1",
      "apparatus": "E01,EC1",
      "units": "E01,EC1",
      "unitCount": "2",
      "primaryTopic": "MED",
      "commandUnits": "",
      "dedupeKey": "INCIDENT-32467"
    }
  },
  {
    "runNumber": "32468",
    "rawCode": "MED",
    "timestamp": "2026-06-17T20:20:41.494015-04:00",
    "address": "600 Block Tower Plz",
    "extra": {
      "incidentNumber": "32468",
      "run_id": "32468",
      "address": "600 Block Tower Plz",
      "rawType": "MED",
      "typeCode": "MED",
      "alert": "10",
      "alertType": "combinedIncident",
      "activePlatoon": "P1",
      "apparatus": "EC10",
      "units": "EC10",
      "unitCount": "1",
      "primaryTopic": "MED",
      "commandUnits": "",
      "dedupeKey": "INCIDENT-32468"
    }
  },
  {
    "runNumber": "32470",
    "rawCode": "MED",
    "timestamp": "2026-06-17T20:48:46.301145-04:00",
    "address": "500 Block Glenbrook Street",
    "extra": {
      "incidentNumber": "32470",
      "run_id": "32470",
      "address": "500 Block Glenbrook Street",
      "rawType": "MED",
      "typeCode": "MED",
      "alert": "10",
      "alertType": "combinedIncident",
      "activePlatoon": "P1",
      "apparatus": "EC8",
      "units": "EC8",
      "unitCount": "1",
      "primaryTopic": "MED",
      "commandUnits": "",
      "dedupeKey": "INCIDENT-32470"
    }
  },
  {
    "runNumber": "32469",
    "rawCode": "MED",
    "timestamp": "2026-06-17T20:48:48.686298-04:00",
    "address": "1000 Block Greendale Road",
    "extra": {
      "incidentNumber": "32469",
      "run_id": "32469",
      "address": "1000 Block Greendale Road",
      "rawType": "MED",
      "typeCode": "MED",
      "alert": "10",
      "alertType": "combinedIncident",
      "activePlatoon": "P1",
      "apparatus": "E24,EC6",
      "units": "E24,EC6",
      "unitCount": "2",
      "primaryTopic": "MED",
      "commandUnits": "",
      "dedupeKey": "INCIDENT-32469"
    }
  },
  {
    "runNumber": "32471",
    "rawCode": "FLIFT",
    "timestamp": "2026-06-17T20:56:46.672255-04:00",
    "address": "3141 Blenheim Way",
    "extra": {
      "incidentNumber": "32471",
      "run_id": "32471",
      "address": "3141 Blenheim Way",
      "rawType": "FLIFT",
      "typeCode": "FLIFT",
      "alert": "10",
      "alertType": "combinedIncident",
      "activePlatoon": "P1",
      "apparatus": "E20",
      "units": "E20",
      "unitCount": "1",
      "primaryTopic": "FLIFT",
      "commandUnits": "",
      "dedupeKey": "INCIDENT-32471"
    }
  },
  {
    "runNumber": "32472",
    "rawCode": "MED",
    "timestamp": "2026-06-17T21:00:46.406109-04:00",
    "address": "1100 Block Mt Rushmore Way",
    "extra": {
      "incidentNumber": "32472",
      "run_id": "32472",
      "address": "1100 Block Mt Rushmore Way",
      "rawType": "MED",
      "typeCode": "MED",
      "alert": "10",
      "alertType": "combinedIncident",
      "activePlatoon": "P1",
      "apparatus": "E16,EC13",
      "units": "E16,EC13",
      "unitCount": "2",
      "primaryTopic": "MED",
      "commandUnits": "",
      "dedupeKey": "INCIDENT-32472"
    }
  },
  {
    "runNumber": "32473",
    "rawCode": "MED",
    "timestamp": "2026-06-17T21:08:47.846593-04:00",
    "address": "3600 Block Laredo Drive",
    "extra": {
      "incidentNumber": "32473",
      "run_id": "32473",
      "address": "3600 Block Laredo Drive",
      "rawType": "MED",
      "typeCode": "MED",
      "alert": "10",
      "alertType": "combinedIncident",
      "activePlatoon": "P1",
      "apparatus": "EC9",
      "units": "EC9",
      "unitCount": "1",
      "primaryTopic": "MED",
      "commandUnits": "",
      "dedupeKey": "INCIDENT-32473"
    }
  },
  {
    "runNumber": "32476",
    "rawCode": "MED",
    "timestamp": "2026-06-17T21:20:50.717341-04:00",
    "address": "800 Block S Broadway",
    "extra": {
      "incidentNumber": "32476",
      "run_id": "32476",
      "address": "800 Block S Broadway",
      "rawType": "MED",
      "typeCode": "MED",
      "alert": "10",
      "alertType": "combinedIncident",
      "activePlatoon": "P1",
      "apparatus": "EC12",
      "units": "EC12",
      "unitCount": "1",
      "primaryTopic": "MED",
      "commandUnits": "",
      "dedupeKey": "INCIDENT-32476"
    }
  },
  {
    "runNumber": "32475",
    "rawCode": "MED",
    "timestamp": "2026-06-17T21:20:53.221390-04:00",
    "address": "700 Block Bennett Avenue",
    "extra": {
      "incidentNumber": "32475",
      "run_id": "32475",
      "address": "700 Block Bennett Avenue",
      "rawType": "MED",
      "typeCode": "MED",
      "alert": "10",
      "alertType": "combinedIncident",
      "activePlatoon": "P1",
      "apparatus": "EC10,RS1",
      "units": "EC10,RS1",
      "unitCount": "2",
      "primaryTopic": "MED",
      "commandUnits": "",
      "dedupeKey": "INCIDENT-32475"
    }
  },
  {
    "runNumber": "32474",
    "rawCode": "MED",
    "timestamp": "2026-06-17T21:20:56.215412-04:00",
    "address": "600 Block Old Frankfort Circle",
    "extra": {
      "incidentNumber": "32474",
      "run_id": "32474",
      "address": "600 Block Old Frankfort Circle",
      "rawType": "MED",
      "typeCode": "MED",
      "alert": "10",
      "alertType": "combinedIncident",
      "activePlatoon": "P1",
      "apparatus": "EC5",
      "units": "EC5",
      "unitCount": "1",
      "primaryTopic": "MED",
      "commandUnits": "",
      "dedupeKey": "INCIDENT-32474"
    }
  },
  {
    "runNumber": "32480",
    "rawCode": "MED",
    "timestamp": "2026-06-17T21:24:50.116306-04:00",
    "address": "2000 Block Versailles Road",
    "extra": {
      "incidentNumber": "32480",
      "run_id": "32480",
      "address": "2000 Block Versailles Road",
      "rawType": "MED",
      "typeCode": "MED",
      "alert": "10",
      "alertType": "combinedIncident",
      "activePlatoon": "P1",
      "apparatus": "E14,EC1",
      "units": "E14,EC1",
      "unitCount": "2",
      "primaryTopic": "MED",
      "commandUnits": "",
      "dedupeKey": "INCIDENT-32480"
    }
  }
]